{"timestamp":1691541073418.3008,"data":{"788":{"7":1223,"N":"SeeiAge"},"1349":{"7":964,"N":"FloosWorld"},"3647":{"7":858,"N":"Kapibarin"},"4971":{"7":1272,"N":"Enf"},"9561":{"7":973,"N":"[TuKn]JoseliasHero"},"10011":{"7":836,"N":"Angry TacoZ"},"10050":{"7":1099,"N":"Battery-acid"},"10946":{"7":1175,"N":"DeJake"},"11251":{"7":1064,"N":"Musar Akino"},"11619":{"7":1106,"N":"Straelboga"},"11956":{"7":1130,"N":"Drakhaon"},"23548":{"7":1449,"N":"Frédéric Chopin"},"36584":{"7":1531,"N":"ShadowCrystallux"},"37913":{"7":986,"N":"cryptomamador"},"53755":{"7":973,"N":"Fats"},"57808":{"7":1003,"N":"Zano1974"},"59478":{"7":950,"N":"Luugolas"},"60896":{"7":869,"N":"johnobrien98"},"81899":{"7":963,"N":"Gualord"},"85772":{"7":880,"N":"adv lavajato"},"113825":{"7":927,"N":"TheLastTeuton"},"116353":{"7":1198,"N":"tavoo"},"119515":{"7":887,"N":"alex2s"},"122115":{"7":1114,"N":"WRMD_Saracen"},"130765":{"7":1037,"N":"DICTATOR"},"131953":{"7":1348,"N":"natkhattj"},"133889":{"7":788,"N":"DressyApollo635"},"145085":{"7":1141,"N":"mnav92"},"161937":{"7":1088,"N":"Elais James Corey"},"162158":{"7":1214,"N":"Maximus Robespierrus"},"163904":{"7":1147,"N":"[DAO] Halvtand"},"183560":{"7":968,"N":"ArChiVe"},"184422":{"7":1392,"N":"[HC] Käptn BrixBart"},"191105":{"7":746,"N":"xiscosb"},"191122":{"7":976,"N":"Gullix"},"193097":{"7":828,"N":"antidarklight"},"195422":{"7":1138,"N":"the black fella"},"196609":{"7":1182,"N":"Gabellius"},"197751":{"7":1897,"N":"GL.Nili"},"197930":{"7":1865,"N":"T90Official"},"209172":{"7":1156,"N":"Blither86"},"209754":{"7":1322,"N":"Fenrir"},"210350":{"7":1269,"N":"GdR_Tonno"},"210636":{"7":1124,"N":"黑暗时刻"},"212517":{"7":1041,"N":"kAPi"},"213355":{"7":1623,"N":"RoR | Kamigawa"},"215404":{"7":1068,"N":"King Harry IV"},"215498":{"7":1645,"N":"SaladEsc"},"217353":{"7":990,"N":"Chimi Kyle"},"219288":{"7":1252,"N":"CelticCyborg"},"220144":{"7":1204,"N":"TruePaladin"},"220548":{"7":947,"N":"whodies"},"221929":{"7":1431,"N":"Kunsito"},"223576":{"7":1224,"N":"Sihing Mo"},"225232":{"7":1010,"N":"Willian_II"},"225767":{"7":1138,"N":"Combi| VivifanTV105"},"226861":{"7":1287,"N":"_Mich_"},"227935":{"7":1307,"N":"DarkLoki"},"229195":{"7":1342,"N":"kingnothing"},"229775":{"7":773,"N":"k4z3"},"230108":{"7":1232,"N":"Blackhunt"},"230475":{"7":1832,"N":"El_Matador"},"230581":{"7":774,"N":"MagnAnduriL"},"231765":{"7":1275,"N":"Comrade Tarkovsky"},"232112":{"7":1158,"N":"Tintenroller"},"232366":{"7":695,"N":"Spartan"},"232606":{"7":1343,"N":"Delta"},"232702":{"7":1109,"N":"J4MMYD0D93R"},"233302":{"7":1197,"N":"TORAZ"},"233324":{"7":1491,"N":"[HoL] Citizen Lame"},"233776":{"7":1496,"N":"Pbeke"},"234184":{"7":1007,"N":"athijuan"},"235796":{"7":998,"N":"CryptoGam3r"},"238842":{"7":1239,"N":"Vane"},"239029":{"7":1047,"N":"Bryks"},"239183":{"7":849,"N":"BluntPikoo420"},"240176":{"7":1143,"N":"Bierzantiner"},"240668":{"7":1107,"N":"QUEEN2Y CHONG 尾号5496"},"241432":{"7":1218,"N":"Helbisch"},"241991":{"7":1124,"N":"[BÜN] Pat_Star"},"243127":{"7":1386,"N":"Failey"},"244504":{"7":996,"N":"tarmineldur"},"246837":{"7":765,"N":"Johan"},"248283":{"7":784,"N":"danijel ilic"},"249430":{"7":1544,"N":"Av3stan"},"249515":{"7":1078,"N":"Agner"},"249919":{"7":1252,"N":"Fool of a Took"},"250087":{"7":933,"N":"Superkiwifruit"},"251668":{"7":1388,"N":"Daniez"},"251937":{"7":836,"N":"Copec"},"254645":{"7":1637,"N":"Avlid_aoe/Twitch"},"255999":{"7":1337,"N":"Firenzo"},"256882":{"7":956,"N":"Whizzy the Elephant"},"257392":{"7":1266,"N":"JonnyJellyfish"},"257795":{"7":1485,"N":"[VL] Karonte"},"258827":{"7":1111,"N":"kiry[RUS]"},"260106":{"7":1453,"N":"Rex Caedis"},"262063":{"7":1120,"N":"RadRed609"},"262331":{"7":1168,"N":"twitch.tv/shiderplays"},"263311":{"7":1161,"N":"Gogolito3000"},"264192":{"7":1224,"N":"-Gore-"},"264543":{"7":916,"N":"AimingWinehouse"},"265163":{"7":1377,"N":"CHRISTOP"},"265901":{"7":1227,"N":"Time Wasted"},"265970":{"7":1002,"N":"Angry Arab"},"267799":{"7":1001,"N":"CurledPear45161"},"267857":{"7":1495,"N":"DanMT"},"269205":{"7":1400,"N":"Phenytoin"},"270315":{"7":1685,"N":"Dratek"},"270639":{"7":964,"N":"Godar14"},"271546":{"7":1545,"N":"gerard"},"271920":{"7":1222,"N":"[Noob] issimus"},"272224":{"7":1420,"N":"cM´ | TheFallen"},"272983":{"7":1196,"N":"BasicallyBebe"},"274288":{"7":1323,"N":"Jackstone9595"},"275226":{"7":1071,"N":"Aiuda"},"275589":{"7":1309,"N":"AceW"},"275730":{"7":703,"N":"Dragon Wizard"},"277769":{"7":1183,"N":"LeosMind"},"278280":{"7":1258,"N":"NightCrawler"},"278983":{"7":967,"N":"perky"},"279098":{"7":1234,"N":"CaBeR_ator"},"279480":{"7":1320,"N":"Blackwing"},"280305":{"7":966,"N":"dance1047812"},"280923":{"7":1587,"N":"RL Matten"},"281567":{"7":1295,"N":"PWT_m24stefan"},"283035":{"7":1417,"N":"AVJack"},"283384":{"7":1335,"N":"[Valhalla] The Otter One"},"286476":{"7":1266,"N":"zupaman"},"287296":{"7":1225,"N":"Coroju ☆☆☆"},"289834":{"7":1324,"N":"outis"},"289899":{"7":1190,"N":"Juicy45"},"290245":{"7":973,"N":"Lonach"},"290340":{"7":1558,"N":"Pez"},"291029":{"7":1374,"N":"[NuMa] Angel_Brutal"},"292038":{"7":1193,"N":"11 | J-Alex-Maister"},"292924":{"7":1006,"N":"tromto"},"293970":{"7":1262,"N":"[DH]Howl Jenkins"},"294595":{"7":1358,"N":"Atula King"},"295707":{"7":1097,"N":"svecko"},"297842":{"7":776,"N":"Random_AUS"},"300565":{"7":1501,"N":"Wean Dinchester"},"301023":{"7":1485,"N":"Ethan"},"301659":{"7":1289,"N":"Jivadesbois"},"304051":{"7":1042,"N":"Osk"},"304436":{"7":1301,"N":"Josh"},"305940":{"7":1080,"N":"Decko"},"306446":{"7":1084,"N":"[IMGG] Zaniocz"},"306782":{"7":1266,"N":"bibaopardo_"},"306975":{"7":1054,"N":"wimpyspud"},"308049":{"7":1162,"N":"man5351"},"312654":{"7":1044,"N":"Parascelsus"},"313524":{"7":888,"N":"GladiusDecimus"},"313591":{"7":1155,"N":"BSHammer"},"319094":{"7":1092,"N":"Casual Male, Extra Large"},"320579":{"7":1077,"N":"Red Horse"},"322402":{"7":968,"N":"BigBossBrowne"},"323730":{"7":995,"N":"Dfghjkl03"},"323976":{"7":978,"N":"Cryptosaurus"},"324295":{"7":1025,"N":"Kalakukulu"},"325360":{"7":1147,"N":"ford933"},"326307":{"7":921,"N":"moschehm"},"329773":{"7":1156,"N":"PTL_passthesugar"},"330041":{"7":1092,"N":"TJ1020"},"330140":{"7":1105,"N":"UndeadCretin"},"330871":{"7":995,"N":"Muss187"},"331402":{"7":928,"N":"TimelessTie1484"},"332890":{"7":1092,"N":"MrJaykey"},"333354":{"7":1212,"N":"Spoxm4n"},"333605":{"7":1143,"N":"The Flagxpert"},"335285":{"7":1235,"N":"Patman"},"338576":{"7":781,"N":"babufrik8313"},"339570":{"7":1159,"N":"[BRANCA] Ale Vai"},"340252":{"7":1125,"N":"SX"},"357795":{"7":1750,"N":"DracKeN"},"358501":{"7":1503,"N":"[BADAS] Claut One"},"363406":{"7":1155,"N":"Hornemoney"},"372435":{"7":914,"N":"Don Mateo"},"372715":{"7":940,"N":"MAIGOD"},"374060":{"7":1255,"N":"The Dalai Alex"},"374618":{"7":857,"N":"Achilles9595"},"377398":{"7":1115,"N":"Franky"},"377399":{"7":1345,"N":"GGWP"},"377614":{"7":1023,"N":"Unknown"},"378047":{"7":1227,"N":"el jardín"},"380189":{"7":964,"N":"As"},"382940":{"7":970,"N":"Macacão Alcoólatra"},"383710":{"7":1195,"N":"Nico203"},"384826":{"7":1559,"N":"Yelur"},"388596":{"7":1188,"N":"Pangolin ;,,;"},"392877":{"7":961,"N":"CrazyBa2na"},"393942":{"7":1108,"N":"Avatar Tako"},"394592":{"7":890,"N":"ricard"},"395345":{"7":1192,"N":"toshy62"},"396178":{"7":958,"N":"AM | Inviten a Popeye"},"399346":{"7":955,"N":"weaver"},"399803":{"7":1198,"N":"Baby Yoda"},"400021":{"7":879,"N":"Can of Corn Carl"},"400139":{"7":1212,"N":"Gumndor"},"400661":{"7":986,"N":"Alcatraz"},"406484":{"7":964,"N":"AfroNinja"},"407362":{"7":961,"N":"teen843"},"409748":{"7":1809,"N":"Capoch"},"412636":{"7":1661,"N":"Bubbagump"},"418568":{"7":1104,"N":"[VL] Dubhe"},"419047":{"7":1308,"N":"党国的恩情还不完"},"422631":{"7":1355,"N":"therealhotsoup"},"425059":{"7":1057,"N":"AUGUSTUS"},"429905":{"7":1441,"N":"Lord Lee So Cacti"},"430968":{"7":1392,"N":"letzteÖlung"},"439835":{"7":1398,"N":"Steve"},"440650":{"7":956,"N":"xCONTORTIONISTx"},"449312":{"7":908,"N":"Fat_Hamm"},"449711":{"7":955,"N":"Knyaz_alex"},"451212":{"7":1234,"N":"Ulfaith"},"451621":{"7":982,"N":"[CLR]Bazinga"},"453331":{"7":1268,"N":"Mickelson"},"453483":{"7":1213,"N":"Vheissu"},"454875":{"7":1033,"N":"Mormegil27"},"456077":{"7":1038,"N":"Middletts AOE"},"456457":{"7":1136,"N":"[LOTD]_Sid"},"457321":{"7":1525,"N":"RoK | Marihuana"},"460516":{"7":1431,"N":"Wayne"},"463440":{"7":1285,"N":"[IO] Nojo"},"465827":{"7":1167,"N":"BorkJutsu"},"466784":{"7":1128,"N":"NEPAFIX on YouTube (back pain)"},"466797":{"7":1278,"N":"0$$I-13"},"466851":{"7":1108,"N":"OLP_Alexso"},"467829":{"7":961,"N":"Liberation"},"468255":{"7":1185,"N":"PiDi"},"470181":{"7":1093,"N":"Corby Tender"},"477544":{"7":1036,"N":"小白兔"},"478050":{"7":1014,"N":"miguelanfac"},"479614":{"7":1101,"N":"Marcus Aurelius"},"483240":{"7":1314,"N":"Funny__Liquid"},"483528":{"7":1132,"N":"Cloneclown"},"492059":{"7":970,"N":"Milan Studnička"},"496017":{"7":1110,"N":"Mr. Muscle"},"496669":{"7":886,"N":"Omegon"},"500411":{"7":1310,"N":"Bismarck"},"501422":{"7":823,"N":"Macanas69"},"503650":{"7":1206,"N":"[NAUT]SausageGuy"},"504072":{"7":1124,"N":"custerlives44"},"504121":{"7":1635,"N":"[GAX]andrade"},"505237":{"7":1076,"N":"Itgetsdarker"},"507452":{"7":888,"N":"Turbo-Jesus-3000"},"508383":{"7":959,"N":"turok"},"508637":{"7":932,"N":"Sotiris Nitro"},"512786":{"7":1351,"N":"Supersonic Rocketship"},"514730":{"7":1226,"N":"PatataMaxtex"},"527729":{"7":1009,"N":"MasterofPun"},"531562":{"7":985,"N":"BIGPILGRIM2598"},"536750":{"7":1050,"N":"SolariumBolek"},"536967":{"7":1115,"N":"NoMad"},"542712":{"7":1217,"N":"koen1sch.-"},"543582":{"7":1408,"N":"大型陸龜"},"543833":{"7":1066,"N":"black_teal"},"546731":{"7":1017,"N":"Mr. Curse"},"549431":{"7":986,"N":"[RPTea] Renrew"},"558577":{"7":931,"N":"TOMB"},"559783":{"7":1116,"N":"Paito Anderson"},"562787":{"7":969,"N":"adalbert01997"},"570416":{"7":992,"N":"felipe_mveiga"},"570431":{"7":1105,"N":"kamilo_g_o"},"570486":{"7":1103,"N":"seaguloftime"},"573282":{"7":1732,"N":"LACA | Terz"},"574484":{"7":1361,"N":"Apis"},"575055":{"7":1430,"N":"D•F•S | Optimus"},"579811":{"7":944,"N":"The Mohawk"},"582263":{"7":1211,"N":"Elionwy"},"594665":{"7":1305,"N":"Siêu tàng hình"},"599353":{"7":959,"N":"beenjaa"},"603396":{"7":948,"N":"almittas"},"606925":{"7":1200,"N":"Holy Assassin"},"609457":{"7":1175,"N":"tima_1999"},"621084":{"7":998,"N":"我的龜TOYOTA又粗"},"621657":{"7":1201,"N":"Geschmeido"},"625354":{"7":904,"N":"sebasssssst"},"625614":{"7":1152,"N":"Dog"},"626669":{"7":1139,"N":"cristianfayad"},"628189":{"7":842,"N":"Lalaria"},"629801":{"7":950,"N":"douglascnc"},"636913":{"7":993,"N":"Kearney"},"644624":{"7":1035,"N":"Dr. Wurst"},"646984":{"7":1061,"N":"Botticelli"},"649406":{"7":824,"N":"next2755"},"650650":{"7":610,"N":"Catalonia4ever"},"652559":{"7":1162,"N":"PANGLIMA"},"655078":{"7":1096,"N":"YungTinio"},"660980":{"7":879,"N":"derarty"},"661296":{"7":888,"N":"facusoca96"},"663329":{"7":939,"N":"51515426"},"663555":{"7":927,"N":"hera02ekh"},"663847":{"7":840,"N":"Atrositus"},"664051":{"7":1019,"N":"Atacani"},"664950":{"7":679,"N":"blackbean"},"665742":{"7":767,"N":"jonathan200020200020"},"669631":{"7":1109,"N":"Madewi"},"672850":{"7":1106,"N":"Iskro"},"673427":{"7":1427,"N":"AOKI_Thanouille"},"673687":{"7":805,"N":"FIXXIUS-01"},"677671":{"7":867,"N":"Epics Lhama"},"678646":{"7":1107,"N":"asmith9455"},"680804":{"7":1056,"N":"supBruh"},"681029":{"7":846,"N":"emanresu"},"681171":{"7":1162,"N":"PapyGunz_YT"},"690902":{"7":1247,"N":"Monsepuseladden"},"694081":{"7":1030,"N":"DOGETUS"},"696377":{"7":1104,"N":"m1lky"},"696559":{"7":1024,"N":"TSwizzle"},"698780":{"7":975,"N":"Moluscol"},"699745":{"7":1284,"N":"charttyler"},"702307":{"7":925,"N":"KnightlyDeeds"},"708226":{"7":1031,"N":"Barbarasurada"},"712321":{"7":1112,"N":"BENTOR"},"713778":{"7":1311,"N":"Whoopsie"},"715704":{"7":1421,"N":"DarkPaladinX"},"718934":{"7":1360,"N":"hellg0lem"},"722034":{"7":1179,"N":"[HvU] DAPOEBLER"},"722041":{"7":1071,"N":"FAMILIA GÓMEZ"},"723264":{"7":903,"N":"RoWarrior"},"724698":{"7":1113,"N":"[LBA] Cerealjames"},"725253":{"7":918,"N":"mikeespin"},"730232":{"7":1089,"N":"nessy"},"733980":{"7":853,"N":"Feuinter"},"737456":{"7":846,"N":"ScapeDokter1"},"744030":{"7":801,"N":"MachoPower1772"},"746777":{"7":1597,"N":"nanimaren"},"751981":{"7":964,"N":"JS"},"754943":{"7":1078,"N":"Comte Clos"},"755337":{"7":1041,"N":"Smoothie"},"757161":{"7":1264,"N":"The O.G. Manbeast"},"758012":{"7":974,"N":"gamer_365"},"759767":{"7":1321,"N":"Millo"},"763979":{"7":949,"N":"mattrobertson15"},"770583":{"7":1625,"N":"twitch.tv/streetpeteaoc"},"771885":{"7":1156,"N":"Poncho"},"773205":{"7":879,"N":"geekerd"},"773547":{"7":703,"N":"KeylessThrone96"},"779130":{"7":1197,"N":"Crola"},"790769":{"7":1136,"N":"Matius"},"791952":{"7":451,"N":"Chritchlow"},"794692":{"7":1233,"N":"TheBull"},"796566":{"7":1069,"N":"Princeroux"},"796908":{"7":1234,"N":"Agron7"},"820124":{"7":1223,"N":"SAD SCAM GAME"},"823541":{"7":1090,"N":"Andrew the Great"},"823583":{"7":1117,"N":"cro55b0w"},"832955":{"7":1034,"N":"Star_Mie"},"836433":{"7":1249,"N":"Burak"},"838896":{"7":1143,"N":"custard"},"838916":{"7":1324,"N":"CrippledGod"},"841136":{"7":1149,"N":"Thrynity"},"870805":{"7":1147,"N":"Ryzz"},"872890":{"7":1086,"N":"BenObear"},"875751":{"7":1069,"N":"TheBoss94"},"878845":{"7":867,"N":"hakangerin"},"882252":{"7":937,"N":"ewingx16"},"886971":{"7":847,"N":"Tannerrrrite990"},"889773":{"7":862,"N":"IMI2442"},"890569":{"7":0,"N":"Crista Acerifolius"},"897737":{"7":869,"N":"specialforces2009"},"907464":{"7":1763,"N":"Howl.Cyclops"},"909627":{"7":1050,"N":"_WWP_Viper"},"911511":{"7":817,"N":"NoName"},"911649":{"7":938,"N":"fonsii91"},"912523":{"7":1520,"N":"Alneryus"},"921446":{"7":1293,"N":"[GER] Paeco"},"927033":{"7":1181,"N":"Josh"},"928535":{"7":1240,"N":"ortix"},"938639":{"7":1612,"N":"Salted Pepper"},"938977":{"7":1002,"N":"Bzilla"},"951203":{"7":1544,"N":"T90"},"954115":{"7":1176,"N":"Bombacı Mülayim"},"957300":{"7":955,"N":"Fanch'"},"958282":{"7":905,"N":"GroovyPetard"},"959596":{"7":715,"N":"kevinandres.1999"},"968655":{"7":1366,"N":"PmpC"},"968984":{"7":1363,"N":"[BadStart] LeoGalda"},"973388":{"7":924,"N":"bbastian"},"976699":{"7":1074,"N":"Sera"},"985494":{"7":1417,"N":"Lord Brosiah"},"988882":{"7":696,"N":"Nightfire9834"},"991477":{"7":1238,"N":"Fibos Nachos"},"991524":{"7":938,"N":"TOMMINGER"},"994370":{"7":1403,"N":"D•F•S | Blade"},"999662":{"7":1273,"N":"lukewarmweeb"},"1001109":{"7":1079,"N":"Marts"},"1017911":{"7":927,"N":"THE ASIANBULL"},"1025291":{"7":769,"N":"Bahamut Zapaton"},"1027001":{"7":1081,"N":"LordAlcol"},"1028470":{"7":1260,"N":"Decently large eggplant"},"1035882":{"7":1192,"N":"Mariotellop"},"1042228":{"7":1090,"N":"TíoHo Tlaltecuhtli"},"1045947":{"7":1135,"N":"文小刀"},"1062980":{"7":1326,"N":"DeaH"},"1068640":{"7":863,"N":"ch.sa.big"},"1069573":{"7":1266,"N":"Souches"},"1094168":{"7":1052,"N":"Recyclops"},"1097593":{"7":1474,"N":"Gabolandia5000"},"1101998":{"7":1037,"N":"sa.albarracin630"},"1105692":{"7":1152,"N":"twistingmidin"},"1109845":{"7":844,"N":"[2ZKA] VonWegen"},"1119211":{"7":1016,"N":"LockyNorrys"},"1125441":{"7":1090,"N":"✪ Fractila"},"1130594":{"7":1240,"N":"Stubenrocker"},"1132594":{"7":1256,"N":"Jazzes O'Rozes"},"1137086":{"7":1607,"N":"shiXo.#"},"1146561":{"7":1128,"N":"IndeanCondor"},"1150580":{"7":958,"N":"fertrujillo25"},"1151160":{"7":1356,"N":"Trude1965"},"1158065":{"7":1298,"N":"BO21 | Limmonada"},"1159622":{"7":1024,"N":"IJustMightJust"},"1162334":{"7":1130,"N":"sLDemocrazy"},"1163547":{"7":958,"N":"[D1]悕衋xixi"},"1166634":{"7":1153,"N":"Rogan_29"},"1168824":{"7":1148,"N":"Mark-sy"},"1174547":{"7":1122,"N":"MrtmX1"},"1177662":{"7":1450,"N":"Smash"},"1178073":{"7":1072,"N":"Crazy_Owl"},"1179568":{"7":1093,"N":"The Dude"},"1184877":{"7":1265,"N":"Cirion"},"1185240":{"7":1149,"N":"llvllaxou"},"1193486":{"7":807,"N":"RoidTank"},"1193732":{"7":1418,"N":"snowshawnskate"},"1195006":{"7":1097,"N":"Jofess das Brotkehlchen"},"1196917":{"7":1279,"N":"Klemens"},"1197410":{"7":1041,"N":"Sir Knight"},"1201524":{"7":1240,"N":"KenE5000"},"1204236":{"7":968,"N":"*- ToToF -*"},"1205387":{"7":1069,"N":"Disgruntled Goat"},"1211725":{"7":1074,"N":"Tiberio"},"1217542":{"7":1176,"N":"Oltinox"},"1228770":{"7":1272,"N":"tiagobellodi"},"1232856":{"7":1222,"N":"[IO] jimmyjames59"},"1233856":{"7":1071,"N":"Floop"},"1236487":{"7":764,"N":"Roll$"},"1251448":{"7":933,"N":"ZombieDaleEarnhardt"},"1253161":{"7":1166,"N":"Shrug"},"1261338":{"7":1123,"N":"Kornfed"},"1263827":{"7":889,"N":"Lord Edar"},"1272485":{"7":1093,"N":"till"},"1283478":{"7":905,"N":"Fizure  ツ"},"1309031":{"7":758,"N":"Zulame000"},"1310289":{"7":1178,"N":"Bequeath14"},"1311235":{"7":964,"N":"Jared G"},"1311588":{"7":1073,"N":"[BJTOX]Quemerorg"},"1318399":{"7":981,"N":"croj92"},"1320131":{"7":1319,"N":"Hippieee"},"1323111":{"7":697,"N":"老司机嘿嘿嘿"},"1326628":{"7":1047,"N":"zapafta"},"1327701":{"7":1208,"N":"xander"},"1331017":{"7":1346,"N":"Lengua"},"1332385":{"7":1458,"N":"katzzlikemeowmix"},"1333398":{"7":840,"N":"JediHobbit613"},"1335927":{"7":1064,"N":"gachimuchi"},"1340778":{"7":678,"N":"Deathstar"},"1341594":{"7":943,"N":"allaith"},"1352812":{"7":1261,"N":"Herkaderkadoo"},"1354937":{"7":1102,"N":"AntsInMyEyesJohnson"},"1363762":{"7":1236,"N":"mardock_mn"},"1364169":{"7":1183,"N":"lunatIC"},"1374864":{"7":856,"N":"WishfulCarrot40"},"1376228":{"7":1055,"N":"lastprune"},"1378127":{"7":1240,"N":"CORP_Lucia Galan"},"1380692":{"7":1030,"N":"Rewide"},"1389289":{"7":1278,"N":"Kreten"},"1392837":{"7":773,"N":"Ezuri"},"1395829":{"7":878,"N":"Trevi"},"1403205":{"7":689,"N":"C O R L E O N E"},"1403347":{"7":1230,"N":"[ GG ] LIMAtador"},"1406852":{"7":923,"N":"soner"},"1410448":{"7":1277,"N":"Kri$"},"1411436":{"7":1188,"N":"GAX | GabeouGabs"},"1411597":{"7":968,"N":"OwnDMoney1313"},"1413238":{"7":1104,"N":"mattyloz"},"1425919":{"7":900,"N":"JGwentworth92"},"1427447":{"7":1409,"N":"Jozzif"},"1429255":{"7":954,"N":"Tschaenu"},"1433753":{"7":910,"N":"eX1st3nce:pain"},"1437877":{"7":1301,"N":"FC | The Finrod Felegund"},"1438162":{"7":1014,"N":"streetcakeavenger"},"1445285":{"7":1219,"N":"enanone"},"1446823":{"7":1136,"N":".#ToTo`"},"1447398":{"7":545,"N":"c.reckemeier"},"1447801":{"7":1262,"N":"Minerva"},"1452443":{"7":1345,"N":"Yoloboy"},"1460610":{"7":965,"N":"ossco_"},"1467023":{"7":1148,"N":"edricsturm"},"1467513":{"7":1012,"N":"Semen Demon"},"1470140":{"7":1383,"N":"Jaco"},"1480531":{"7":643,"N":"finnstar25"},"1482603":{"7":993,"N":"Grug"},"1484664":{"7":1327,"N":"[S1z3] theMole"},"1491458":{"7":1091,"N":"Carterman89"},"1508944":{"7":647,"N":"WarSword"},"1509382":{"7":1233,"N":"Lenni"},"1511346":{"7":1014,"N":"永猎行刑官"},"1513040":{"7":626,"N":"Tomas"},"1513444":{"7":1105,"N":"Arrille"},"1520159":{"7":1479,"N":"lepac"},"1522990":{"7":1205,"N":"Scadufax"},"1523379":{"7":920,"N":"starzrc"},"1535012":{"7":931,"N":"jeffjeffsen"},"1535067":{"7":1462,"N":"Strider"},"1536374":{"7":1221,"N":"ToiDauHang"},"1539092":{"7":1037,"N":"Superju"},"1541225":{"7":1054,"N":"Dreadnoughtus7"},"1544825":{"7":1101,"N":"FoxesCEC"},"1552622":{"7":1164,"N":"HAMPAR"},"1554817":{"7":1399,"N":"Xumpy"},"1556097":{"7":875,"N":"Almondos AllerweltsMandel"},"1564934":{"7":1092,"N":"amacandcheese"},"1569762":{"7":995,"N":"2722027078"},"1570149":{"7":1156,"N":"SebaT420"},"1579751":{"7":991,"N":"carlovacko"},"1580161":{"7":1155,"N":"[MF]"},"1583574":{"7":1144,"N":"Malifalitiko"},"1590271":{"7":1385,"N":"DaGoo"},"1592208":{"7":453,"N":"elquique255"},"1597595":{"7":1302,"N":"Nordyus"},"1607693":{"7":1403,"N":"shegin"},"1610730":{"7":901,"N":"Llibertat"},"1613158":{"7":909,"N":"Nekalaika"},"1613847":{"7":1244,"N":"fcnoth1ing"},"1616045":{"7":1068,"N":"juank93"},"1619518":{"7":1156,"N":"jack.stphn"},"1634857":{"7":1068,"N":"Bebê Demônio"},"1641601":{"7":1027,"N":"CsabiST"},"1656195":{"7":1102,"N":"Tanner"},"1657709":{"7":953,"N":"Pho2Go"},"1662227":{"7":1099,"N":"Moonlight Shadow"},"1663037":{"7":1170,"N":"UBF | malibu_stacy"},"1665676":{"7":1042,"N":"haukush"},"1668882":{"7":1333,"N":"RyskiNinja"},"1670043":{"7":1091,"N":"batan1917"},"1675625":{"7":1147,"N":"MarcoPolo"},"1680281":{"7":1149,"N":"DonKan"},"1680895":{"7":1063,"N":"robmsharp"},"1684016":{"7":1045,"N":"DonVito"},"1689425":{"7":1054,"N":"名字很长很长很长很长"},"1693063":{"7":1208,"N":"WeX Dawg"},"1694092":{"7":1350,"N":"Jason_AOE"},"1698869":{"7":1043,"N":"elgalle02"},"1705555":{"7":1078,"N":"purplephoenix"},"1706790":{"7":994,"N":"lektrol"},"1712333":{"7":1040,"N":"Cangaceiro9760"},"1716425":{"7":977,"N":"Scotch_Bonnet"},"1716511":{"7":1120,"N":"scouzzr"},"1745016":{"7":1389,"N":"CORP_Marcus"},"1745578":{"7":994,"N":"sojutime"},"1747909":{"7":1393,"N":"duckdowN"},"1749981":{"7":732,"N":"LittleDwarf"},"1751534":{"7":1187,"N":"peace"},"1753071":{"7":1301,"N":"schober_thomas"},"1754629":{"7":1894,"N":"SalzZ_classicpro"},"1767170":{"7":1084,"N":"PoTitoz"},"1768269":{"7":1078,"N":"gua"},"1774700":{"7":1073,"N":"spearman3"},"1775957":{"7":547,"N":"trivialreality"},"1779682":{"7":627,"N":"galactus"},"1783832":{"7":1169,"N":"[VEP] Assamita18"},"1787202":{"7":1227,"N":"小火虫"},"1796702":{"7":946,"N":"dankhurst"},"1800074":{"7":1338,"N":"cmfabian"},"1805289":{"7":834,"N":"leinormendez190890"},"1806925":{"7":1038,"N":"Pundabar"},"1816819":{"7":1306,"N":"Landshark"},"1820280":{"7":944,"N":"TScottRun"},"1822789":{"7":1148,"N":"twitch yifahn"},"1826244":{"7":829,"N":"Chimlele"},"1826578":{"7":1233,"N":"ShawnKnight"},"1827288":{"7":790,"N":"Goon"},"1828787":{"7":860,"N":"Jevers777"},"1834800":{"7":962,"N":"SyL1on"},"1835659":{"7":1149,"N":"JAS"},"1838385":{"7":1037,"N":"Jake"},"1840362":{"7":850,"N":"Indie"},"1847174":{"7":1288,"N":"SS_nb__"},"1849427":{"7":968,"N":"Akoros"},"1849670":{"7":1288,"N":"你可以再次投降"},"1863757":{"7":1170,"N":"Roar"},"1863903":{"7":939,"N":"Pinocchio"},"1865587":{"7":1033,"N":"josloayza"},"1868119":{"7":1071,"N":"[Fs] Minduca"},"1868779":{"7":1279,"N":"Leshan"},"1872814":{"7":1027,"N":"Auror"},"1873346":{"7":259,"N":"alexanderus"},"1876194":{"7":818,"N":"Bazza"},"1877284":{"7":720,"N":"cambo"},"1879350":{"7":989,"N":"ilPerozzi"},"1880526":{"7":1214,"N":"EXILE | Gamelua"},"1884971":{"7":1018,"N":"Hagerbows"},"1885922":{"7":1421,"N":"edz97"},"1886617":{"7":1328,"N":"[Fx、]AirDk"},"1887687":{"7":974,"N":"Dani_Jiren"},"1887918":{"7":1329,"N":"OG daddy"},"1894849":{"7":1429,"N":"CR | NamelessGuy"},"1895918":{"7":1005,"N":"JLC"},"1896526":{"7":1063,"N":"L0sha"},"1902440":{"7":831,"N":"Ordinary Housecrab"},"1902995":{"7":556,"N":"Legion8484"},"1915586":{"7":980,"N":"RutherfordTheBrave"},"1922194":{"7":1098,"N":"Dormage"},"1929016":{"7":931,"N":"MexRex"},"1929114":{"7":1245,"N":"Màtyàs Hunyadi"},"1929234":{"7":1102,"N":"andrea.shady38"},"1929548":{"7":1204,"N":"PeterPetauri"},"1931760":{"7":1165,"N":"Pentatax"},"1932371":{"7":535,"N":"mastroianniluca88"},"1939430":{"7":1104,"N":"matagilis"},"1943316":{"7":1103,"N":"rushman"},"1943851":{"7":1009,"N":"Do_y"},"1944921":{"7":992,"N":"Sakuneti Le-Preckson"},"1945281":{"7":1681,"N":"[CHEM] Smokey"},"1949249":{"7":1304,"N":"Torres Torres"},"1955049":{"7":902,"N":"IV. GON"},"1956229":{"7":852,"N":"rodrigomoreno365"},"1957876":{"7":1307,"N":"Mengudaii"},"1959289":{"7":397,"N":"GL"},"1962480":{"7":782,"N":"ronaldoepq"},"1975122":{"7":871,"N":"Alcon Rojo"},"1978798":{"7":1257,"N":"omnomnomnivore"},"1981276":{"7":911,"N":"alejandrowille"},"1981408":{"7":934,"N":"JuanDavidHerol"},"1985198":{"7":814,"N":"Aldo-"},"1987320":{"7":1061,"N":"LudwigvanKnethoden"},"1991544":{"7":1788,"N":"JonnyOhneHa"},"1996645":{"7":772,"N":"martinako004"},"1999444":{"7":1461,"N":"AOKI_GworK_67"},"2005048":{"7":1063,"N":"alteco_99"},"2009883":{"7":891,"N":"Mobius One"},"2019025":{"7":1328,"N":"nj.mosqueira"},"2019202":{"7":972,"N":"Avimsil"},"2019643":{"7":1017,"N":"Comissando"},"2029744":{"7":1144,"N":"LGN. Guillelimp"},"2031103":{"7":819,"N":"Hlias_Olympiakos"},"2033976":{"7":1203,"N":"Mannaus"},"2035461":{"7":998,"N":"Alejandroooooo"},"2042066":{"7":859,"N":"alphabeard"},"2042473":{"7":1222,"N":"Kloerb"},"2045040":{"7":742,"N":"SEDARO91"},"2045777":{"7":873,"N":"posimons"},"2050264":{"7":1457,"N":"Winters"},"2053455":{"7":1046,"N":"NMP"},"2053579":{"7":952,"N":"Yattara"},"2056258":{"7":973,"N":"Syz"},"2059485":{"7":766,"N":"ObjetCiseaux901"},"2064220":{"7":1098,"N":"jeanfe95"},"2064286":{"7":1220,"N":"veganmAyoE"},"2067157":{"7":1059,"N":"Broken Viking"},"2071735":{"7":981,"N":"macmij"},"2072875":{"7":1005,"N":"paul.flyingwhale"},"2075681":{"7":1220,"N":"CORP_Qeetsa"},"2090196":{"7":1354,"N":"matias_dka"},"2090904":{"7":842,"N":"Knoeriefast"},"2092945":{"7":961,"N":"HAZMAT"},"2100003":{"7":888,"N":"penninckstijn"},"2101660":{"7":1060,"N":"Sneeuwgans"},"2103871":{"7":696,"N":"PrismaInsel7248"},"2104198":{"7":992,"N":"vedattufan1"},"2105546":{"7":1046,"N":"Право Имею"},"2108538":{"7":1061,"N":"pmeridiem"},"2109220":{"7":1129,"N":"deadly neighbour"},"2109240":{"7":917,"N":"luis"},"2110390":{"7":1048,"N":"Shnotty"},"2111365":{"7":956,"N":"King JC1524"},"2111578":{"7":1197,"N":"Bean goose"},"2112475":{"7":1483,"N":"catastrophe"},"2113208":{"7":1022,"N":"ScoobyU"},"2113685":{"7":817,"N":"hoel"},"2114555":{"7":661,"N":"Stialoggia"},"2117146":{"7":936,"N":"gaab"},"2117487":{"7":648,"N":"carlosbernalcova"},"2118843":{"7":1257,"N":"jaykobus"},"2119468":{"7":1029,"N":"gmeet15"},"2130052":{"7":987,"N":"Part Time Gamer"},"2132243":{"7":954,"N":"ibrahim"},"2139187":{"7":937,"N":"qiglesias"},"2142155":{"7":852,"N":"watsonycrick"},"2147516":{"7":727,"N":"vahrenkampj"},"2149398":{"7":942,"N":"DR_goldnib8"},"2152411":{"7":829,"N":"PKD_La Choike"},"2153422":{"7":739,"N":"sblaya"},"2156751":{"7":991,"N":"Hamzeh"},"2158471":{"7":1051,"N":"MATT_FRY"},"2158880":{"7":999,"N":"atitititi"},"2159056":{"7":1118,"N":"Oxelot"},"2161078":{"7":1250,"N":"TioNachoooi"},"2165075":{"7":906,"N":"los nombres no existen"},"2178556":{"7":1052,"N":"Mycologist"},"2186527":{"7":1182,"N":"Calvohp"},"2186763":{"7":1071,"N":"EuroKiller"},"2188417":{"7":810,"N":"Madmanmed"},"2189320":{"7":1056,"N":"Stone"},"2191803":{"7":1089,"N":"Cancelled"},"2191954":{"7":729,"N":"rich_jess"},"2192867":{"7":1226,"N":"Luke"},"2193935":{"7":877,"N":"amx"},"2197304":{"7":455,"N":"idle moments"},"2202558":{"7":952,"N":"andunestel"},"2203464":{"7":923,"N":"Rubenius"},"2205013":{"7":813,"N":"derek"},"2208351":{"7":1214,"N":"jules_4"},"2222341":{"7":854,"N":"lexus182"},"2223575":{"7":881,"N":"YCZS"},"2225213":{"7":1022,"N":"fjarist"},"2227707":{"7":1653,"N":"Goatmeister"},"2233059":{"7":937,"N":"ortega78200"},"2239994":{"7":1182,"N":"Bloo"},"2241255":{"7":895,"N":"Barranas"},"2241414":{"7":964,"N":"José Santillán"},"2241992":{"7":984,"N":"ZORO"},"2248850":{"7":1010,"N":"LivreChene790"},"2251596":{"7":1043,"N":"Dark Age Farmer"},"2253348":{"7":1087,"N":"BingoBente"},"2256409":{"7":1119,"N":"DuckConfit"},"2257562":{"7":1138,"N":"R2Shef2"},"2259617":{"7":1009,"N":"mandro_891"},"2273281":{"7":580,"N":"fedev79"},"2276789":{"7":1139,"N":"Advanced Farming Research Centre"},"2283399":{"7":1357,"N":"TM MrLoKuRa"},"2289248":{"7":1516,"N":"vevi"},"2289937":{"7":1120,"N":"NapoDooM"},"2293048":{"7":1071,"N":"LeoBoy/11♌"},"2293609":{"7":1225,"N":"Mike"},"2294138":{"7":1103,"N":"ZA"},"2295504":{"7":1633,"N":"KH_Eren"},"2295601":{"7":985,"N":"Tiguan Winnig display"},"2298672":{"7":897,"N":"fobimarras"},"2299215":{"7":1078,"N":"SMOC | PEGASE50100"},"2302541":{"7":1381,"N":"Sonny"},"2303338":{"7":846,"N":"RELIF89"},"2304247":{"7":1035,"N":"Nickoc84"},"2305483":{"7":774,"N":"SoyGeorge70"},"2306252":{"7":841,"N":"Tricresta"},"2308033":{"7":1002,"N":"The King"},"2308751":{"7":1111,"N":"[MK5] Purraneta"},"2309468":{"7":1611,"N":"DreamCl"},"2324735":{"7":1171,"N":"EDINHO"},"2327451":{"7":755,"N":"carlitos el destructor"},"2329095":{"7":1110,"N":"segundosominson"},"2333680":{"7":1143,"N":"Grossiegros"},"2347544":{"7":749,"N":"benoit.ma"},"2350809":{"7":1210,"N":"Juannoesminombrexd"},"2355198":{"7":630,"N":"bang bang"},"2355442":{"7":972,"N":"BUTTSHARK"},"2360919":{"7":1349,"N":"GoodGuy"},"2363863":{"7":1168,"N":"C4BR4"},"2374380":{"7":932,"N":"[NuMa]chamandres"},"2385419":{"7":1297,"N":"WiSeMaN"},"2389844":{"7":1138,"N":"niquito0912"},"2390532":{"7":755,"N":"Oenomaus"},"2397051":{"7":1332,"N":"Lagger (-_-)'"},"2401846":{"7":877,"N":"\"EL CHEFFE\""},"2402335":{"7":1132,"N":"TheKhadku"},"2403609":{"7":969,"N":"armvalcap"},"2406520":{"7":1028,"N":"Greybell"},"2407045":{"7":591,"N":"Cap9789"},"2407737":{"7":1084,"N":"Velzi17"},"2408998":{"7":1137,"N":"ro.salamano"},"2410227":{"7":995,"N":"Kakalokoatlik"},"2412823":{"7":1211,"N":"PaulMac"},"2415706":{"7":1286,"N":"Fiškál"},"2416176":{"7":1162,"N":"polop88"},"2417988":{"7":937,"N":"Supertoñin"},"2419773":{"7":1773,"N":"Kugelblitz"},"2419870":{"7":595,"N":"spam"},"2426003":{"7":932,"N":"P3dret3"},"2430137":{"7":1054,"N":"ionatan"},"2432658":{"7":1141,"N":"Kurbads"},"2434331":{"7":721,"N":"Principal"},"2436017":{"7":1243,"N":"[AFK]The_Offwo"},"2436114":{"7":914,"N":"SuperNinjaGod911"},"2440091":{"7":1314,"N":"chimbonde"},"2440169":{"7":1017,"N":"Supertanker"},"2442965":{"7":1133,"N":"Frak"},"2443235":{"7":1023,"N":"JavaSE"},"2443909":{"7":1003,"N":"Tinchi88"},"2446338":{"7":707,"N":"Chirlo1984"},"2449750":{"7":1540,"N":"cuak"},"2450920":{"7":1109,"N":"gott_im_gen"},"2451134":{"7":662,"N":"expat"},"2452496":{"7":1075,"N":"dmalign d great"},"2454373":{"7":1159,"N":"Paquita Industrial"},"2457349":{"7":936,"N":"joelviteladelacruz"},"2462680":{"7":577,"N":"pierrelebonbucheron"},"2466093":{"7":888,"N":"carlocecco97"},"2469375":{"7":1123,"N":"jason613480918"},"2471498":{"7":996,"N":"Esosspoppenonn"},"2471800":{"7":988,"N":"拓荒者小郭哥"},"2471823":{"7":1060,"N":"ruben14ci"},"2475306":{"7":921,"N":"Pharamir"},"2477440":{"7":1167,"N":"amoelpan"},"2482098":{"7":1377,"N":"Faneth"},"2484032":{"7":671,"N":"es00g"},"2488501":{"7":1086,"N":"[AoT] ☣ Rapidler™ ☣"},"2489419":{"7":1067,"N":"Luijki"},"2489524":{"7":535,"N":"KugelDerivat686"},"2495109":{"7":1308,"N":"Han"},"2497486":{"7":830,"N":"kikillo77"},"2499170":{"7":1216,"N":"rodrigo.mr"},"2499841":{"7":815,"N":"Mr. Rabbit"},"2499887":{"7":787,"N":"Yeet_Me_Into_A_Volcano_Thnx"},"2502515":{"7":1562,"N":"Koerbel"},"2512659":{"7":707,"N":"tashava"},"2513163":{"7":1206,"N":"The Senate"},"2513296":{"7":835,"N":"julianacional_"},"2515228":{"7":1089,"N":"alelexl"},"2517035":{"7":922,"N":"[NQN] The Robert's"},"2521620":{"7":1168,"N":"hakan ozkafa"},"2526742":{"7":492,"N":"Aalok4194"},"2526890":{"7":912,"N":"absbuiles"},"2528238":{"7":835,"N":"Stella."},"2532176":{"7":1360,"N":"Oii"},"2536422":{"7":1314,"N":"Kirac"},"2539449":{"7":648,"N":"chudleythedrip"},"2540031":{"7":1148,"N":"bondfiti"},"2543798":{"7":1099,"N":"erik.hudcovsky1"},"2559087":{"7":1097,"N":"DABNE"},"2562222":{"7":1312,"N":"mifan93"},"2567678":{"7":1039,"N":"tanboon"},"2572621":{"7":1184,"N":"Closed † ./"},"2574042":{"7":856,"N":"JOKER"},"2575709":{"7":1023,"N":"GodNicki"},"2575839":{"7":1006,"N":"borraznajera"},"2576833":{"7":1178,"N":"mjb    2"},"2578845":{"7":984,"N":"mirdle"},"2581746":{"7":991,"N":"Flammendes Käthchen"},"2585238":{"7":890,"N":"Osckar508"},"2585509":{"7":965,"N":"Tupac Juancho"},"2585856":{"7":702,"N":"fernandojim"},"2586749":{"7":995,"N":"The_Lolmeister"},"2586802":{"7":821,"N":".:JimmyJam:."},"2589331":{"7":1583,"N":"AntagonisT"},"2592892":{"7":699,"N":"Sudaca"},"2593681":{"7":927,"N":"alfonso.alanisj"},"2596159":{"7":1106,"N":"Glorified Suburban Alcoholic"},"2599793":{"7":1177,"N":"The_Economist"},"2602142":{"7":1057,"N":"juann.sosa1778"},"2608346":{"7":853,"N":"HazeOne"},"2619767":{"7":973,"N":"BOOmSlAngSNAKE"},"2620313":{"7":1183,"N":"nIKO"},"2625885":{"7":1473,"N":"T......T.......s"},"2627091":{"7":1096,"N":"HD_Montu"},"2631079":{"7":1255,"N":"PN|Amorsito"},"2632311":{"7":1081,"N":"RagnarL92"},"2632812":{"7":1476,"N":"[BF] Emgo Pceyan"},"2634437":{"7":1130,"N":"deadlane farmer ♪Keeb8"},"2640100":{"7":935,"N":"GLHF"},"2640697":{"7":482,"N":"Tangy"},"2642963":{"7":1261,"N":"BO21 | CrewColombia"},"2644643":{"7":1045,"N":"giosotto91"},"2648009":{"7":946,"N":"Warquito"},"2649938":{"7":985,"N":"Kuxce"},"2654577":{"7":1598,"N":"Ozone"},"2655139":{"7":1078,"N":"CoffeeRhyme7095"},"2656684":{"7":918,"N":"sarek91"},"2658171":{"7":948,"N":"PITON | Mateoignacio"},"2663624":{"7":1056,"N":"hrad_cz"},"2665874":{"7":1167,"N":"GoldNudel"},"2670575":{"7":1142,"N":"GorDocho"},"2671094":{"7":1013,"N":"Erwin_del_Kaos"},"2673862":{"7":1312,"N":"Mr_Eh"},"2674016":{"7":1051,"N":"КаппаПушка"},"2678579":{"7":1114,"N":"Saif Da Sublime"},"2681227":{"7":758,"N":"eric"},"2681270":{"7":1147,"N":"Facundin"},"2682540":{"7":1085,"N":"Hodur"},"2689079":{"7":1060,"N":"ivandrago8005"},"2706933":{"7":939,"N":"arrayan"},"2708054":{"7":940,"N":"My Nan Rips Cans"},"2709115":{"7":1281,"N":"[ByC]_Acero"},"2709408":{"7":772,"N":"larbedan"},"2720704":{"7":1222,"N":"Mr Gonzalo"},"2725838":{"7":898,"N":"Carabues"},"2728445":{"7":1029,"N":"Serpent"},"2733600":{"7":1038,"N":"aurangzaib.zahoor"},"2736369":{"7":1005,"N":"Dark_Lion"},"2740030":{"7":1017,"N":"Folklore"},"2740919":{"7":723,"N":"sneah9"},"2747191":{"7":1156,"N":"Fusilier649"},"2749002":{"7":586,"N":"Ciegocleto"},"2749860":{"7":1345,"N":"putih"},"2754403":{"7":1132,"N":"Valente__14"},"2757843":{"7":857,"N":"stepheneb90"},"2765252":{"7":1027,"N":"jose.jimenezr"},"2765757":{"7":1089,"N":"Hunter33"},"2770310":{"7":1061,"N":"Art"},"2770682":{"7":981,"N":"masterjd23"},"2776661":{"7":1046,"N":"[JgR] ReyMp13"},"2779868":{"7":920,"N":"rayito.465"},"2781393":{"7":1015,"N":"Stuby14"},"2783660":{"7":1672,"N":"Fox.Sebastian"},"2783887":{"7":1074,"N":"?"},"2787704":{"7":1175,"N":"RBase96"},"2789600":{"7":1235,"N":"amamepeteribi"},"2791724":{"7":890,"N":"86969829"},"2792305":{"7":1550,"N":"XEVER | BL4CKITO"},"2796519":{"7":1006,"N":"SRK"},"2797779":{"7":907,"N":"Baron Von Herzenberger"},"2810449":{"7":1052,"N":"Pabmgt"},"2813971":{"7":914,"N":"oVitorAdriano"},"2821779":{"7":1684,"N":"DS_Pela"},"2830428":{"7":869,"N":"Rey Charles7151"},"2830833":{"7":1034,"N":"StandAlone"},"2832621":{"7":753,"N":"mohitag4563"},"2836937":{"7":1137,"N":"Alez"},"2838786":{"7":1140,"N":"lethal_meganoob"},"2840779":{"7":1123,"N":"vagos.jmauro"},"2841109":{"7":501,"N":"ronnieestes88"},"2844234":{"7":1060,"N":"76561199066388432"},"2850158":{"7":635,"N":"GrayHat"},"2854511":{"7":925,"N":"ScaryBeatle3799"},"2855984":{"7":1234,"N":"no bebo agua si doy besos ricos"},"2858362":{"7":1900,"N":"GL.JorDan_AoE"},"2865852":{"7":1102,"N":"Twojorge2626"},"2867404":{"7":917,"N":"GutterStomp"},"2868742":{"7":939,"N":"kraken6669488"},"2870652":{"7":1138,"N":"IBreak VII"},"2871521":{"7":1394,"N":"Hello how are you?"},"2873825":{"7":1000,"N":"CarePato22"},"2878223":{"7":965,"N":"Kate"},"2885582":{"7":577,"N":"Jorge el Grande"},"2889415":{"7":1176,"N":"afpinedac"},"2891203":{"7":717,"N":"Magnific1982"},"2894032":{"7":800,"N":"WinterWolf"},"2901975":{"7":1346,"N":"[KO19] Davide"},"2903801":{"7":1003,"N":"nizu9110"},"2905240":{"7":1160,"N":"togio96"},"2909935":{"7":1461,"N":"kk900826"},"2917219":{"7":625,"N":"alves_nilo"},"2917790":{"7":1361,"N":"dbs00"},"2919023":{"7":1058,"N":"Chubi"},"2920003":{"7":1185,"N":"Barón de la Cerveza"},"2921459":{"7":1214,"N":"Xtreme | Tuco"},"2929008":{"7":1060,"N":"Joyboy_Luffy"},"2930377":{"7":1283,"N":"[WG] onglenuh"},"2941892":{"7":1024,"N":"Marti l'Huma"},"2944434":{"7":1621,"N":"HOWL.Yax"},"2944629":{"7":804,"N":"joseivanconceicao"},"2946214":{"7":982,"N":"[XEVER]Guyanito"},"2948234":{"7":969,"N":"erikonrombosman"},"2949534":{"7":1050,"N":"eurrere"},"2949666":{"7":856,"N":"SetaSojiro01"},"2949977":{"7":909,"N":"CapitanPijama"},"2951749":{"7":1066,"N":"iluvplex"},"2952899":{"7":491,"N":"tobiasjohn"},"2954730":{"7":1439,"N":"Dr. Pepper"},"2960804":{"7":836,"N":"emanuelmoris68"},"2962832":{"7":1032,"N":"NooBNesHTayN"},"2964148":{"7":1442,"N":"Parrywentos"},"2966822":{"7":868,"N":"Peroksizon"},"2967126":{"7":1009,"N":"Pestilence"},"2975180":{"7":630,"N":"christopherpark5588"},"2982016":{"7":1074,"N":"XCrossbyX"},"2983505":{"7":1190,"N":"Combi | Paloma 52"},"2983673":{"7":1005,"N":"mastergibbs94"},"2984529":{"7":1213,"N":"GENERAL TSO SAUCE"},"2994554":{"7":864,"N":"Jogando"},"2994961":{"7":956,"N":"GORDONEZ"},"3003153":{"7":1142,"N":"Lugoe"},"3003185":{"7":1246,"N":"Surjanpeter"},"3006184":{"7":1032,"N":"d0m0nator"},"3007539":{"7":1070,"N":"Blue Blurks"},"3008156":{"7":987,"N":"Drfrondizi"},"3012130":{"7":1061,"N":"tessie"},"3020605":{"7":845,"N":"Pass The Pickle"},"3021611":{"7":794,"N":"cristobaltco"},"3023356":{"7":893,"N":"Enishi"},"3033932":{"7":1047,"N":"Old Renjo"},"3036075":{"7":991,"N":"HackerDev"},"3038235":{"7":1190,"N":"XEVER | MEYER"},"3042740":{"7":970,"N":"hasenkürbis"},"3047350":{"7":1101,"N":"Juansedav95"},"3054040":{"7":1129,"N":"jorgeberkhoff.1995"},"3056061":{"7":1079,"N":"[LAK] Nihil Terror"},"3056504":{"7":877,"N":"Lady Palmerita"},"3060436":{"7":1083,"N":"LEUNG1313"},"3060795":{"7":776,"N":"kezarpa"},"3061191":{"7":897,"N":"TheLongestNameEver"},"3061410":{"7":1176,"N":"SJ"},"3074812":{"7":1081,"N":"[ECU] C.LOPEZ"},"3080882":{"7":853,"N":"j.garcia-22"},"3083464":{"7":1339,"N":"Epsilon475"},"3084963":{"7":1136,"N":"Poisn"},"3086077":{"7":916,"N":"Kvrozz"},"3088811":{"7":919,"N":"点金冰女"},"3091161":{"7":1103,"N":"yAureus"},"3091289":{"7":878,"N":"MagicMax"},"3094462":{"7":582,"N":"專門打小楊的男人"},"3095614":{"7":758,"N":"draapen_87"},"3097100":{"7":1080,"N":"nicolasestebanpescio"},"3098497":{"7":729,"N":"storreso9973"},"3100522":{"7":761,"N":"Novais"},"3119418":{"7":1259,"N":"Kachz"},"3119522":{"7":976,"N":"BrickyArrow1990"},"3124030":{"7":982,"N":"abaryl"},"3134507":{"7":950,"N":"NEO"},"3137150":{"7":923,"N":"C_ZÛ"},"3142890":{"7":916,"N":"jparrachea"},"3143301":{"7":1031,"N":"dahuhe"},"3147786":{"7":1115,"N":"Espolón de Aquitania"},"3149262":{"7":626,"N":"dooontcryy63"},"3163126":{"7":1082,"N":"MagicJK"},"3165946":{"7":1461,"N":"[BRANCA] Tomass.97"},"3170507":{"7":1071,"N":"mavs19"},"3172784":{"7":869,"N":"hard2explain"},"3178351":{"7":984,"N":"shotelaitactico"},"3189822":{"7":1177,"N":"Rumo3141"},"3190763":{"7":976,"N":"Möbi56"},"3191944":{"7":1096,"N":"Resurrection21"},"3194355":{"7":1100,"N":"Layetezelzel"},"3203031":{"7":949,"N":"零度光年"},"3216495":{"7":1280,"N":"legeds"},"3221000":{"7":1187,"N":"jdtuell"},"3237762":{"7":1163,"N":"Ucanbay"},"3238819":{"7":769,"N":"seb.riojasj"},"3239502":{"7":973,"N":"TheRedox"},"3249688":{"7":1095,"N":"jswan"},"3252938":{"7":1417,"N":"Figuin"},"3257940":{"7":1067,"N":"whitehawk"},"3260124":{"7":935,"N":"TheScruff"},"3273479":{"7":973,"N":"bodunn12"},"3276436":{"7":790,"N":"Giampy12"},"3285258":{"7":1555,"N":"Combi | Kiss"},"3294828":{"7":1159,"N":"[AnnD] SmarttGuyy"},"3296280":{"7":1120,"N":"MFC J20G"},"3306144":{"7":1003,"N":"LEE333"},"3306988":{"7":1124,"N":"HUSK"},"3307956":{"7":902,"N":"[La14]S4DD4M"},"3315872":{"7":812,"N":"esg"},"3318300":{"7":1170,"N":"(PNG) Adrogue_PR"},"3319951":{"7":1066,"N":"无畏斯拉克"},"3321848":{"7":658,"N":"Shrings"},"3322870":{"7":976,"N":"pollito"},"3327173":{"7":1319,"N":"cocotg"},"3331564":{"7":1214,"N":"ramax"},"3342905":{"7":1044,"N":"Jimi Jones"},"3347693":{"7":1080,"N":"Samuelito"},"3354630":{"7":933,"N":"Armador"},"3357289":{"7":1639,"N":"Big Dota"},"3358688":{"7":679,"N":"D_WILL Legend"},"3363471":{"7":915,"N":"TitoKgB"},"3367257":{"7":653,"N":"Hochlord Poli Warder"},"3369575":{"7":1035,"N":"Turbo1518"},"3370438":{"7":1096,"N":"Noyssi"},"3371802":{"7":889,"N":"AntFelsina"},"3372240":{"7":886,"N":"dolaytoda"},"3373281":{"7":1345,"N":"The French Kiddo"},"3375978":{"7":864,"N":"Letal44"},"3396184":{"7":1050,"N":"guillo1978"},"3402169":{"7":941,"N":"recuu"},"3404226":{"7":986,"N":"Jaderyac"},"3416540":{"7":1255,"N":"[Legacy]Rian23"},"3419327":{"7":887,"N":"John Kennedy"},"3420175":{"7":1112,"N":"Froggy"},"3442365":{"7":1011,"N":"[Krush] clemclxm"},"3446882":{"7":1883,"N":"HOWL.Kozmonot"},"3456044":{"7":1161,"N":"quasiuki"},"3460243":{"7":933,"N":"MaikolCorners"},"3464416":{"7":949,"N":"The_Rush"},"3471054":{"7":1290,"N":"[ECU]Paladin_Mongol"},"3478557":{"7":956,"N":"Thales"},"3493844":{"7":792,"N":"Peristalt"},"3496962":{"7":1061,"N":"KrazyKajun"},"3500428":{"7":1015,"N":"JakubCZ"},"3502833":{"7":1027,"N":"conde drac"},"3509656":{"7":1114,"N":"oki"},"3522012":{"7":1434,"N":"OX | FIGO"},"3525164":{"7":918,"N":"RVHC"},"3531020":{"7":1099,"N":"rUiN"},"3542146":{"7":993,"N":"MUR DIOTUS"},"3554104":{"7":1050,"N":"bupf"},"3556121":{"7":1298,"N":"lIlㅣIlIㅣllIㅣIlIㅣllI"},"3575950":{"7":876,"N":"Panty 69 Sniffer"},"3579582":{"7":854,"N":"TOMASTOSELLO"},"3604031":{"7":782,"N":"liam198926"},"3606342":{"7":474,"N":"火云邪神"},"3606586":{"7":1004,"N":"Glorval"},"3641593":{"7":707,"N":"wasamara3040"},"3665377":{"7":1104,"N":"Afisicote"},"3696200":{"7":1337,"N":"Manolo"},"3711601":{"7":943,"N":"Aldeano"},"3712481":{"7":1577,"N":"Suryavarman"},"3751013":{"7":952,"N":"whyteRON"},"3783092":{"7":957,"N":"Kike.Haedo"},"3783631":{"7":844,"N":"thedittu"},"3814256":{"7":988,"N":"fmoraisc"},"3816000":{"7":1165,"N":"mateconpan"},"3816609":{"7":1432,"N":"twitch.tv/i_amkaito"},"3822593":{"7":1143,"N":"Lajoie"},"3852724":{"7":1005,"N":"Vince"},"3854156":{"7":1148,"N":"iwan.beats"},"3857280":{"7":998,"N":"LARUMBE"},"3857923":{"7":1167,"N":"marienkäferle"},"3867075":{"7":904,"N":"calvoj550"},"3867529":{"7":1163,"N":"3lw3"},"3867568":{"7":1161,"N":"Daniil"},"3879070":{"7":911,"N":"`|`|reX®™"},"3885004":{"7":1029,"N":"jlozano15"},"3885336":{"7":1312,"N":"bigtiddygoth"},"3896013":{"7":980,"N":"KrackaWitCheese"},"3900359":{"7":1040,"N":"Jouspal25"},"3903432":{"7":1256,"N":"Shogi8900"},"3908581":{"7":1021,"N":"jeanstyles"},"3910549":{"7":876,"N":"Storm"},"3910717":{"7":894,"N":"vfifcerf19141918"},"3912152":{"7":931,"N":"ValarMorghulis"},"3914287":{"7":939,"N":"Humitas_con_tomate"},"3916549":{"7":1135,"N":"Léon"},"3918711":{"7":1306,"N":"lupoml7"},"3941126":{"7":1059,"N":"[TUSC] 0dannyboy10"},"3948615":{"7":1079,"N":"Twuggle"},"3950763":{"7":896,"N":"moresky"},"3957492":{"7":1093,"N":"[Decrepit] Trader123452621"},"3963718":{"7":869,"N":"michael"},"3972536":{"7":632,"N":"Fasol1no"},"4008781":{"7":832,"N":"Amon9R"},"4009079":{"7":1162,"N":"Skawawa"},"4010454":{"7":1169,"N":"The Bear"},"4017146":{"7":1050,"N":"NestorNotabilis"},"4020937":{"7":837,"N":"jejelapoudre"},"4022293":{"7":1006,"N":"SurrealCaesar9"},"4023441":{"7":790,"N":"老墨香油"},"4039060":{"7":1057,"N":"MartinStan"},"4040935":{"7":1033,"N":"fralarada"},"4042031":{"7":968,"N":"htr_pba"},"4042971":{"7":1002,"N":"so6"},"4043033":{"7":843,"N":"amand2005"},"4050405":{"7":901,"N":"Pichuls"},"4053446":{"7":1110,"N":"Esbleider"},"4053626":{"7":967,"N":"Conotor"},"4059429":{"7":1063,"N":"sneaky steve"},"4059858":{"7":607,"N":"Лоуренс Лимбурге"},"4067166":{"7":1206,"N":"feshark"},"4068688":{"7":816,"N":"lubo.viluda"},"4084003":{"7":600,"N":"BMCM !"},"4092440":{"7":1113,"N":"bluey"},"4093310":{"7":981,"N":"chihscoot"},"4102441":{"7":1141,"N":"Hun power"},"4104675":{"7":624,"N":"曹操"},"4105819":{"7":1021,"N":"Coyotesolo"},"4119145":{"7":620,"N":"JitteryStorm92"},"4126656":{"7":400,"N":"TiagoPiNgUiN"},"4127083":{"7":1016,"N":"sog"},"4137174":{"7":746,"N":"Phatty_Biltong"},"4143876":{"7":659,"N":"SebaMG29960"},"4150679":{"7":963,"N":"FrushMush"},"4151133":{"7":981,"N":"Pistachos_baratos"},"4152144":{"7":1132,"N":"HD_cristian cubo"},"4152931":{"7":1051,"N":"TheBondiola"},"4160073":{"7":900,"N":"Messiah1287"},"4161009":{"7":900,"N":"meine-e-mail-adresse"},"4162663":{"7":867,"N":"daftquotient837"},"4173107":{"7":891,"N":"TonyThreeKnees"},"4181796":{"7":1060,"N":"Godly Llama"},"4189798":{"7":1106,"N":"Napoleon"},"4189902":{"7":1067,"N":"X0KA"},"4195016":{"7":1066,"N":"Hunter"},"4202731":{"7":1033,"N":"blaugrana"},"4207407":{"7":1299,"N":"roma"},"4232196":{"7":945,"N":"odonaires"},"4239537":{"7":983,"N":"Боевой комар NATO"},"4243070":{"7":1099,"N":"beerladin"},"4249973":{"7":1315,"N":"White Knight"},"4252362":{"7":449,"N":"miss de winter"},"4253317":{"7":1198,"N":"DS_Jaspe"},"4257640":{"7":1248,"N":"ominolo"},"4257811":{"7":666,"N":"Kampeador"},"4262096":{"7":1062,"N":"simonbrc"},"4263492":{"7":1034,"N":"Lone Wolf"},"4269212":{"7":930,"N":"Insireus"},"4273374":{"7":1211,"N":"Lobisomem Pidão"},"4273716":{"7":1158,"N":"CHUCK MURDER NOVA"},"4277642":{"7":1264,"N":"knightforchrist_11"},"4286371":{"7":1012,"N":"Luis Jamoninton"},"4288945":{"7":603,"N":"cannkilic"},"4289864":{"7":1127,"N":"HELLBOY"},"4291784":{"7":865,"N":"axreph"},"4292558":{"7":1149,"N":"The_Barba_NegrA"},"4295859":{"7":1240,"N":"Murits"},"4303112":{"7":1056,"N":"chmdy"},"4304921":{"7":1003,"N":"X"},"4310075":{"7":1321,"N":"Flippin Pancakes"},"4312174":{"7":1079,"N":"VivaCristoRey"},"4317369":{"7":821,"N":"tom_jt2"},"4324719":{"7":951,"N":"RyujinnJakka"},"4327711":{"7":1406,"N":"Bean"},"4334780":{"7":920,"N":"4xm"},"4344133":{"7":743,"N":"juanchester"},"4344551":{"7":1119,"N":"CORGI"},"4349959":{"7":1183,"N":"forever_housed"},"4352356":{"7":1027,"N":"709 kilograms of salt"},"4352579":{"7":797,"N":"Vectorz"},"4355878":{"7":1269,"N":"The Flying Dutch Saucer"},"4358388":{"7":1086,"N":"kamikko0322[JPN]"},"4363891":{"7":945,"N":"HuevoGordo"},"4379491":{"7":457,"N":"liegenderHolländer"},"4384678":{"7":1248,"N":"Toota"},"4386051":{"7":762,"N":"emrek"},"4395910":{"7":1127,"N":"Xanthos"},"4397605":{"7":957,"N":"Xiongnu"},"4405839":{"7":824,"N":"Jagu Rassol"},"4411776":{"7":1321,"N":"[SotC] Tarasco"},"4412660":{"7":1150,"N":"GZalex5312"},"4421225":{"7":868,"N":"vicentejoaquin97"},"4423096":{"7":1180,"N":"varun_pikachu"},"4423499":{"7":1004,"N":"TeacherHustle"},"4424340":{"7":884,"N":"Seaside Jack"},"4424588":{"7":797,"N":"sanchezure"},"4428283":{"7":949,"N":"forneromatteo"},"4429443":{"7":1025,"N":"matthewharland"},"4435573":{"7":929,"N":"So Lillo"},"4443635":{"7":1027,"N":"ben695664849"},"4444082":{"7":531,"N":"RAULDEATH666"},"4445732":{"7":927,"N":"Shabby01"},"4448420":{"7":936,"N":"pwnd nub"},"4450310":{"7":1651,"N":"dataidiot"},"4465837":{"7":1091,"N":"juanmelgarejo92"},"4469384":{"7":950,"N":"sidaryildirim"},"4469615":{"7":1307,"N":"King dyranutane"},"4470791":{"7":893,"N":"El Picatripas"},"4474398":{"7":1064,"N":"Ka-Boom"},"4474479":{"7":975,"N":"st1m4"},"4480622":{"7":969,"N":"212_no_312"},"4481535":{"7":883,"N":"Zrínyi Miklós"},"4489393":{"7":979,"N":"DigitalSun"},"4489869":{"7":978,"N":"viridity"},"4491099":{"7":810,"N":"akris_mejo"},"4498744":{"7":1088,"N":"BigBanana"},"4500201":{"7":1059,"N":"Prince"},"4502640":{"7":997,"N":"Lanius"},"4515093":{"7":986,"N":"Syagrius"},"4518506":{"7":1366,"N":"MetalRoX"},"4525153":{"7":1456,"N":"aeternam"},"4525542":{"7":736,"N":"richardholt1971"},"4528621":{"7":1150,"N":"Andrectho"},"4530085":{"7":1025,"N":"1Capitan_Zz1"},"4542696":{"7":1162,"N":"tomas.stepan"},"4544301":{"7":1166,"N":"JASHXL"},"4545137":{"7":1060,"N":"BigGerman"},"4545266":{"7":1158,"N":"TheBigFish"},"4546899":{"7":675,"N":"Eray"},"4547018":{"7":1109,"N":"Bfaster"},"4549077":{"7":890,"N":"Maxime"},"4559788":{"7":880,"N":"andreysher97"},"4560419":{"7":954,"N":"Lord Future"},"4564589":{"7":868,"N":"MisterOF"},"4567875":{"7":1254,"N":"louisdeboz"},"4582638":{"7":885,"N":"codingforlifetime"},"4613397":{"7":960,"N":"g.ulloa"},"4625799":{"7":1126,"N":"the_yard"},"4626912":{"7":930,"N":"Marx15"},"4627039":{"7":1132,"N":"Zvonimir"},"4630497":{"7":835,"N":"REY ACHU4884"},"4648029":{"7":1069,"N":"bleaderr"},"4660112":{"7":808,"N":"pcallahan25820"},"4663736":{"7":805,"N":"BMMStrue"},"4674201":{"7":811,"N":"AnimalNine99679"},"4674874":{"7":774,"N":"ColdM@N"},"4678051":{"7":818,"N":"alexandrew67"},"4682927":{"7":963,"N":"Nesper"},"4703823":{"7":701,"N":"brij198833"},"4717252":{"7":1160,"N":"Fufu apapachon"},"4721004":{"7":938,"N":"istebudur"},"4721599":{"7":829,"N":"guillermoalzamora16"},"4728303":{"7":634,"N":"bugstyle"},"4732583":{"7":620,"N":"w.jack94"},"4732734":{"7":946,"N":"llerena"},"4740278":{"7":644,"N":"N A Ø H C"},"4747930":{"7":753,"N":"Jikato"},"4755870":{"7":872,"N":"dopeydugong"},"4769698":{"7":1231,"N":"Zero"},"4770899":{"7":1076,"N":"Ilneropapa"},"4785780":{"7":952,"N":"facu.k95"},"4789340":{"7":855,"N":"Big_Tasty"},"4790233":{"7":1228,"N":"BierBär"},"4792324":{"7":1492,"N":"montezen"},"4799871":{"7":1238,"N":"CORP_Anakin"},"4810831":{"7":971,"N":"Dijeijesus"},"4816622":{"7":870,"N":"love_88876515"},"4818255":{"7":1024,"N":"chuckmorris6289"},"4818990":{"7":965,"N":"Sciroccoboi16v"},"4824426":{"7":979,"N":"martinluis2011"},"4825885":{"7":1111,"N":"Ninho88"},"4840067":{"7":575,"N":"Haissem71"},"4844040":{"7":1321,"N":"Juicius Maximus"},"4850531":{"7":1037,"N":"elliottnahums"},"4857978":{"7":701,"N":"dario_sn"},"4861482":{"7":638,"N":"hecval77"},"4862231":{"7":698,"N":"edgar.ing2011"},"4863869":{"7":1038,"N":"juanoc"},"4877339":{"7":973,"N":"Great Saif"},"4879268":{"7":744,"N":"полковник госу"},"4883044":{"7":796,"N":"blogos47"},"4884145":{"7":1149,"N":"seyhuncemal"},"4886158":{"7":1274,"N":"欺我无"},"4887547":{"7":1030,"N":"青蛙"},"4888071":{"7":765,"N":"poman8285"},"4906475":{"7":939,"N":"andiskin"},"4906793":{"7":950,"N":"RödeOrm"},"4909031":{"7":871,"N":"Jackdad8"},"4910989":{"7":1210,"N":"Disaster101"},"4916117":{"7":939,"N":"matiascolin_96"},"4917243":{"7":875,"N":"oliverdp2011"},"4918515":{"7":1145,"N":"Dampé"},"4919267":{"7":1255,"N":"TealSeal42"},"4922989":{"7":1155,"N":"jitse"},"4926158":{"7":904,"N":"dantealhz"},"4926384":{"7":1395,"N":"Excommunicado"},"4927976":{"7":949,"N":"DrumSetMan19"},"4930309":{"7":1019,"N":"XXxCoExXX"},"4934795":{"7":1280,"N":"DeuS"},"4948213":{"7":907,"N":"SimGoober"},"4952428":{"7":1392,"N":"Arabia Player2"},"4967280":{"7":864,"N":"VisibleBread457"},"4968600":{"7":982,"N":"Tamaghna Chaudhuri"},"4974784":{"7":889,"N":"pablo_ben"},"4975468":{"7":1192,"N":"Kastaar"},"4996679":{"7":966,"N":"DeViL"},"5004039":{"7":989,"N":"Kedar"},"5008603":{"7":913,"N":"Dacianicuss"},"5010990":{"7":1031,"N":"kai on"},"5017153":{"7":1537,"N":"Nervkeks"},"5019951":{"7":1544,"N":"SH | Toth"},"5020904":{"7":757,"N":"MAFETOS"},"5022034":{"7":982,"N":"Shavn"},"5027871":{"7":1120,"N":"acceleteenor"},"5029884":{"7":900,"N":"Jkeeeeeeeeeeeeee"},"5034694":{"7":931,"N":"Tlitado"},"5036396":{"7":711,"N":"CraftyPoet87778"},"5037632":{"7":1142,"N":"Fingerinthea55"},"5038546":{"7":889,"N":"satoshi.rs"},"5038685":{"7":810,"N":"BELETTI"},"5044054":{"7":1129,"N":"Pimenta\""},"5045761":{"7":1205,"N":"TowerRushsshhh"},"5049792":{"7":1011,"N":"savinbel"},"5073506":{"7":895,"N":"HOBITUN"},"5079284":{"7":910,"N":"noe_alvarado14"},"5083440":{"7":1082,"N":"cartCURT"},"5103626":{"7":1002,"N":"KaraTerzi"},"5112522":{"7":1713,"N":"Josmu"},"5120311":{"7":870,"N":"Boriska78"},"5131240":{"7":1002,"N":"Kaimen8826"},"5139377":{"7":1272,"N":"89sokol89"},"5145801":{"7":1194,"N":"Ingeniero_Beltran"},"5186718":{"7":1251,"N":"Zaryab"},"5187382":{"7":842,"N":"JuneeTheGamer"},"5188554":{"7":1671,"N":"Mr. L'amore"},"5197761":{"7":1004,"N":"HAVE FUN OR LAG"},"5198398":{"7":981,"N":"eletroya"},"5200402":{"7":1020,"N":"Sponsored by Barney"},"5202923":{"7":907,"N":"HppyS1syph0s"},"5205872":{"7":1224,"N":"[GdSur] Juanmpi"},"5207630":{"7":1145,"N":"__elXeneize__"},"5209774":{"7":885,"N":"Dr_Nobs"},"5211328":{"7":1325,"N":"Adrian"},"5212455":{"7":991,"N":"andyfaff"},"5215227":{"7":1005,"N":"cuaiern"},"5216513":{"7":878,"N":"niubi"},"5221573":{"7":990,"N":"Cartel"},"5223140":{"7":1032,"N":"tassimago"},"5251192":{"7":1330,"N":"scheisse"},"5254390":{"7":1078,"N":"kevin11oo"},"5256647":{"7":912,"N":"MurderDitroo"},"5256991":{"7":1174,"N":"__BlAcKPhOeNiX__"},"5284586":{"7":767,"N":"managarmr"},"5285353":{"7":782,"N":"lizandropm1"},"5290829":{"7":984,"N":"Raptor King"},"5293546":{"7":1127,"N":"CR | El Dani"},"5294027":{"7":835,"N":"Indiana Jones"},"5295192":{"7":756,"N":"josuearreola1206"},"5299642":{"7":673,"N":"age Walter"},"5303231":{"7":1538,"N":"_Thefury_"},"5305119":{"7":890,"N":"G@@dB@y"},"5306144":{"7":794,"N":"FREEDOM ISN'T FREE"},"5317881":{"7":879,"N":"piojoso87"},"5321503":{"7":1581,"N":"gamer123"},"5324630":{"7":925,"N":"rictony0738916"},"5329445":{"7":1070,"N":"lag_mayus"},"5329677":{"7":676,"N":"howle paasha"},"5333450":{"7":1166,"N":"mitrokhin1994"},"5333964":{"7":1146,"N":"lynx"},"5339304":{"7":1159,"N":"** whale**"},"5349486":{"7":962,"N":"L'EzzE"},"5351294":{"7":1087,"N":"Smeadrel"},"5353072":{"7":1254,"N":"INKAS | Spadasangrienta"},"5358434":{"7":852,"N":"GoddoG"},"5368182":{"7":1086,"N":"D edelweiss"},"5368855":{"7":1067,"N":"Elba Silon"},"5380736":{"7":1006,"N":"GrumpyNun"},"5388722":{"7":730,"N":"dangerof100"},"5393031":{"7":1319,"N":"ForVengeance"},"5407617":{"7":1072,"N":"eeeee"},"5410978":{"7":791,"N":"karensuzane"},"5411178":{"7":954,"N":"Jean_Batist_Amour"},"5412717":{"7":1078,"N":"Zimmbous"},"5414501":{"7":943,"N":"M4NUX193"},"5418777":{"7":867,"N":"BefriarenBerggren"},"5423160":{"7":763,"N":"Ryan_18"},"5426558":{"7":1141,"N":"garrix13"},"5434606":{"7":1396,"N":"FacuN97"},"5438575":{"7":959,"N":"c_aus_h"},"5453900":{"7":893,"N":"Alpha Robeeert"},"5462150":{"7":1253,"N":"guramata"},"5485769":{"7":1026,"N":"italiankid"},"5511165":{"7":1055,"N":"The_Marsupilami"},"5513337":{"7":1364,"N":"Lord R Sling"},"5513366":{"7":708,"N":"TeKilla"},"5519095":{"7":612,"N":"justy178"},"5526497":{"7":991,"N":"Nougatspeier"},"5529910":{"7":506,"N":"johug"},"5538371":{"7":957,"N":"diego91613"},"5562913":{"7":974,"N":"Ryan"},"5583474":{"7":867,"N":"redhisa"},"5584757":{"7":1379,"N":"DeleteoTC"},"5611817":{"7":961,"N":"jeinsgon"},"5613454":{"7":737,"N":"Tony"},"5615251":{"7":906,"N":"erik_wilbrink"},"5625686":{"7":1286,"N":"BabyDriver_"},"5640413":{"7":892,"N":"valentin.akkord"},"5646724":{"7":1059,"N":"Julianm93"},"5659953":{"7":944,"N":"pfernandezinfo"},"5662573":{"7":1026,"N":"Ulises89"},"5664425":{"7":897,"N":"Matthias"},"5666710":{"7":567,"N":"henryderrick77"},"5668230":{"7":653,"N":"WeighedWig74290"},"5670437":{"7":955,"N":"uLI"},"5682965":{"7":1178,"N":"ivanlpr"},"5686200":{"7":1047,"N":"Rododino"},"5690485":{"7":981,"N":"Général Rob"},"5694787":{"7":1371,"N":"CrozZby"},"5704556":{"7":1168,"N":"gamer1234"},"5705160":{"7":819,"N":"blackwolf cz"},"5708976":{"7":1101,"N":"WrenchThrower"},"5709411":{"7":792,"N":"supermurloc.999"},"5715066":{"7":1030,"N":"lukasperry2"},"5730909":{"7":1076,"N":"miguelpc89"},"5731242":{"7":1079,"N":"y958700"},"5733226":{"7":945,"N":"jonny1797"},"5734826":{"7":1318,"N":"ANTIFA"},"5742773":{"7":1008,"N":"giouli87"},"5751203":{"7":905,"N":"Zingcha"},"5754903":{"7":1423,"N":"twitch.tv/carlosalf1"},"5759996":{"7":855,"N":"chifurinfula"},"5760013":{"7":764,"N":"Cole_17"},"5760229":{"7":995,"N":"mr.remyj"},"5772029":{"7":883,"N":"RenegadeRy"},"5772336":{"7":1172,"N":"lokoivi4"},"5775906":{"7":737,"N":"wittroc"},"5790693":{"7":735,"N":"GalacticBand75"},"5797368":{"7":848,"N":"Mambo"},"5803193":{"7":1057,"N":"CMONT"},"5807238":{"7":910,"N":"patelmodz1"},"5813401":{"7":1043,"N":"Yoyi"},"5815375":{"7":1114,"N":"{ST}the_zar"},"5818351":{"7":1086,"N":"OdinSoN891733"},"5824275":{"7":817,"N":"Achala"},"5831996":{"7":891,"N":"KAOS"},"5832174":{"7":814,"N":"aksariahmetali"},"5838701":{"7":1053,"N":"Assyrian Empire"},"5858968":{"7":1147,"N":"lynx8463"},"5860675":{"7":849,"N":"OwningPrawn50"},"5864208":{"7":1161,"N":"dbbollich"},"5869824":{"7":861,"N":"Mati"},"5870922":{"7":781,"N":"juani.leon"},"5876936":{"7":977,"N":"fattoshala"},"5887665":{"7":988,"N":"GrayTamer2"},"5892992":{"7":1130,"N":"Happy_Irishman68"},"5899239":{"7":866,"N":"2jjeffr72021"},"5900894":{"7":908,"N":"Luisca191007"},"5902090":{"7":1129,"N":"PUM03"},"5903520":{"7":866,"N":"alyssonamiltom"},"5924369":{"7":1182,"N":"Mr Fallouts"},"5927256":{"7":429,"N":"OCTO"},"5927588":{"7":1112,"N":"Whimsical Cheek Clapper"},"5928887":{"7":999,"N":"kevin180"},"5929480":{"7":927,"N":"LordRakaz"},"5939853":{"7":998,"N":"Lady Malbec"},"5945965":{"7":1185,"N":"À jamais insoumise"},"5950415":{"7":1046,"N":"SHAPOCK"},"5959388":{"7":772,"N":"yakudzzza"},"5961610":{"7":959,"N":"YuckyYucca"},"5967011":{"7":1152,"N":"lemon"},"5970614":{"7":1316,"N":"XINGBAO"},"5978864":{"7":906,"N":"Varvatos"},"5983303":{"7":1035,"N":"gastonsanguinetti1995"},"5985919":{"7":1209,"N":"[CHEM] TBomber"},"5986009":{"7":1218,"N":"RichieRich"},"5990582":{"7":536,"N":"Orca"},"5993236":{"7":1114,"N":"ice ice baby"},"6004729":{"7":1010,"N":"2Geese4Bread"},"6017980":{"7":838,"N":"leoxord"},"6034109":{"7":957,"N":"clark.sam.b"},"6036324":{"7":1009,"N":"TW_GOGO"},"6041187":{"7":640,"N":"marceloiltis"},"6053554":{"7":855,"N":"FelipeHaro"},"6069614":{"7":1279,"N":"Charmander Bey"},"6081599":{"7":1027,"N":"[WK] KingRev_"},"6085078":{"7":613,"N":"ondrasczek"},"6092881":{"7":1158,"N":"ursilov05"},"6097252":{"7":783,"N":"nachogalcoba"},"6115589":{"7":979,"N":"AndreasT"},"6118272":{"7":954,"N":"Chen"},"6119137":{"7":940,"N":"jonypugil"},"6119781":{"7":877,"N":"NoName"},"6120448":{"7":782,"N":"bruno.teruggi5"},"6128854":{"7":908,"N":"DonTomazzo90"},"6137483":{"7":933,"N":"Captain H. Penguin"},"6138083":{"7":1010,"N":"Oxymoron"},"6139678":{"7":950,"N":"pieterjanpauwelyn"},"6145620":{"7":932,"N":"Well-willed"},"6150895":{"7":1025,"N":"El Chico De Las Poesías"},"6160820":{"7":1298,"N":"Super Nintendo Chalmers"},"6170898":{"7":953,"N":"z3zaito"},"6172564":{"7":979,"N":"Corvinmatyi"},"6172908":{"7":1120,"N":"xyz13111"},"6174450":{"7":1152,"N":"itchy"},"6174461":{"7":858,"N":"Thor XL"},"6184201":{"7":864,"N":"7sn"},"6187685":{"7":1297,"N":"VLC | 3L0Ki"},"6194694":{"7":1137,"N":"jiri.hradec.jr"},"6197414":{"7":773,"N":"CombinedPlate50"},"6205921":{"7":966,"N":"Ray Sun"},"6207199":{"7":1001,"N":"lianruogu"},"6213210":{"7":917,"N":"Wabbelschwabbel"},"6213297":{"7":996,"N":"Black_Wolf"},"6226087":{"7":898,"N":"jtamayovelez"},"6230625":{"7":1148,"N":"Zeus_VN"},"6231272":{"7":1143,"N":"umbergys"},"6231997":{"7":970,"N":"flo_the_emperor"},"6258879":{"7":690,"N":"//MikoLee//"},"6259055":{"7":780,"N":"1064879312"},"6261373":{"7":1206,"N":"Kyrisser"},"6268904":{"7":1156,"N":"Tonsil"},"6273706":{"7":1207,"N":"caixiaoyu6660075"},"6278119":{"7":1025,"N":"Go Veg"},"6280447":{"7":1640,"N":"HEROID"},"6281891":{"7":774,"N":"爱过."},"6283300":{"7":1165,"N":"AOEKing"},"6291035":{"7":647,"N":"Cyanide SDDA"},"6295810":{"7":1272,"N":"Sangonera"},"6312620":{"7":977,"N":"Julianthedog"},"6317194":{"7":746,"N":"mariano.mereb"},"6324008":{"7":1022,"N":"Mouse"},"6326854":{"7":1152,"N":"Dzakari"},"6333159":{"7":1135,"N":"江河湖海"},"6338734":{"7":695,"N":"DarthMaoriBro"},"6354558":{"7":1052,"N":"Vobby"},"6357049":{"7":968,"N":"Jundi Leads"},"6359412":{"7":1272,"N":"Philip Majboor"},"6361625":{"7":1043,"N":"Norian"},"6365113":{"7":1161,"N":"Smiley"},"6368854":{"7":779,"N":"God1819"},"6384720":{"7":963,"N":"tatosalta"},"6386527":{"7":801,"N":"Nick_Jay_Jordan"},"6388892":{"7":711,"N":"guillermo.arino"},"6392835":{"7":928,"N":"Boomkiller7"},"6393475":{"7":930,"N":"GEPARD RETARDIEU"},"6400347":{"7":900,"N":"LateStarling694"},"6415413":{"7":1058,"N":"camilok24"},"6426559":{"7":1135,"N":"The Venator"},"6429338":{"7":1054,"N":"konvalik"},"6436297":{"7":1004,"N":"Skouz"},"6443741":{"7":1049,"N":"Ogedei5955"},"6446934":{"7":680,"N":"Schrodinger"},"6451580":{"7":705,"N":"GazmoiT"},"6456859":{"7":1215,"N":"bobesft"},"6460476":{"7":621,"N":"llPapis84"},"6460553":{"7":849,"N":"facuudeleva2"},"6487529":{"7":850,"N":"killmeifyoucan"},"6509349":{"7":943,"N":"sampete56"},"6525994":{"7":881,"N":"yazeed-zaw"},"6539870":{"7":861,"N":"MUBS Bot"},"6543235":{"7":992,"N":"sampanie tati banditcamp.com"},"6545619":{"7":640,"N":"Eternal Herald(;"},"6553949":{"7":957,"N":"jaimecaballe"},"6623160":{"7":950,"N":"Bitter Symphony"},"6676580":{"7":1123,"N":"Chainy555"},"6747968":{"7":980,"N":"adison16"},"6758457":{"7":1129,"N":"Reynewam"},"6765639":{"7":779,"N":"Jofan7453"},"6766251":{"7":1062,"N":"TitaLaplan"},"6771826":{"7":750,"N":"Brancaleone6938"},"6772321":{"7":891,"N":"Filippo E R"},"6772856":{"7":968,"N":"Cardboardowl"},"6777641":{"7":785,"N":"markjdallas"},"6793303":{"7":868,"N":"Peekaboo"},"6793400":{"7":401,"N":"人菜但瘾大"},"6794947":{"7":1008,"N":"mohtal"},"6804294":{"7":1178,"N":"Lord Voldemort"},"6804299":{"7":1100,"N":"Caddu"},"6816471":{"7":700,"N":"partidalt88"},"6820660":{"7":936,"N":"LUBIEFRYTKI_3"},"6820724":{"7":944,"N":"goldinggunsandparts"},"6822758":{"7":580,"N":"Atila on Fire 8"},"6832636":{"7":515,"N":"♛LiA♛ ujebal jsom Majlana"},"6837813":{"7":1213,"N":"rgfp15915"},"6838127":{"7":1038,"N":"tiimAvodah"},"6839456":{"7":1183,"N":"[BMAC] POTROHERMANO"},"6840716":{"7":832,"N":"saniuwa"},"6855001":{"7":994,"N":"Kapro"},"6864091":{"7":693,"N":"daperez-13"},"6865344":{"7":1261,"N":"Angel Peñaloza"},"6874878":{"7":835,"N":"Speedyblupi"},"6883104":{"7":753,"N":"sebastian1724"},"6885433":{"7":930,"N":"VANCS"},"6892324":{"7":992,"N":"Angry Bull"},"6894291":{"7":1010,"N":"zer0ths"},"6894486":{"7":1043,"N":"7kimal3rab"},"6896687":{"7":1012,"N":"Iluminati62"},"6924383":{"7":961,"N":"thk_ultra"},"6932991":{"7":785,"N":"Wipuckwanabee"},"7162736":{"7":883,"N":"xi78"},"7181663":{"7":1050,"N":"karasangil"},"7212192":{"7":869,"N":"theEldar"},"7306064":{"7":973,"N":"Norbok"},"7484759":{"7":1221,"N":"RRのwudi"},"7523722":{"7":672,"N":"Wizzard188"},"7550675":{"7":963,"N":"Samniticus"},"7706601":{"7":782,"N":"JUNKYARDDOG420"},"7942890":{"7":875,"N":"reyklieberei"},"8059245":{"7":1045,"N":"Arcantos"},"8091623":{"7":723,"N":"BraggestMars527"},"8197717":{"7":1158,"N":"yzhan293"},"8200571":{"7":894,"N":"Hittus"},"8223898":{"7":955,"N":"Immortalz"},"8248889":{"7":964,"N":"Харконен"},"8278275":{"7":795,"N":"Sanabcull"},"8347289":{"7":722,"N":"123"},"8368870":{"7":1506,"N":"Toto"},"8369205":{"7":946,"N":"jnasuf"},"8391939":{"7":1053,"N":"Hammerbolter"},"8415706":{"7":846,"N":"Detektyw"},"8447899":{"7":1719,"N":"JonnyOha"},"8472909":{"7":961,"N":"Diffusion"},"8480488":{"7":1242,"N":"Đam mê game"},"8535107":{"7":872,"N":"Bacillol"},"8562036":{"7":1369,"N":"Petabyte"},"8569527":{"7":463,"N":"ruhrpottjunge81"},"8576763":{"7":898,"N":"gaspar_8822"},"8608010":{"7":812,"N":"eoskiller"},"8618580":{"7":931,"N":"JustSomeNoob"},"8640578":{"7":894,"N":"marbleking2012"},"8650662":{"7":912,"N":"WayOwner"},"8654320":{"7":1007,"N":"LemonGarlic5614"},"8688068":{"7":965,"N":"123"},"8724140":{"7":675,"N":"Sabevissia"},"8737671":{"7":1133,"N":"晚风与你"},"8765516":{"7":967,"N":"CMONT"},"8793050":{"7":861,"N":"corocota96"},"8822454":{"7":1053,"N":"milaci"},"8824948":{"7":1095,"N":"alex.mov"},"8831801":{"7":815,"N":"fcochacon02"},"8861806":{"7":703,"N":"niubitan"},"8884213":{"7":684,"N":"Abi4205644"},"8894823":{"7":710,"N":"kirem5"},"8901487":{"7":1250,"N":"Sawan"},"8913439":{"7":1236,"N":"Rocket"},"8914598":{"7":961,"N":"Wep0n"},"8928788":{"7":946,"N":"keruinekella"},"8928978":{"7":573,"N":"Guerillero"},"8930279":{"7":915,"N":"elio_delio"},"8939982":{"7":851,"N":"Tio_Torru_75"},"8942652":{"7":867,"N":"YuYuOuO"},"8954939":{"7":1066,"N":"Perdidoin"},"8955002":{"7":1075,"N":"anserak_knadelbi"},"8969953":{"7":1051,"N":"Goldy"},"8977219":{"7":686,"N":"Jose Manuel"},"8987204":{"7":940,"N":"Locomotive712"},"8990647":{"7":1088,"N":"HyNo"},"8998270":{"7":919,"N":"tts.engamb"},"9005637":{"7":935,"N":"endre_csiki"},"9011596":{"7":955,"N":"Villager"},"9013268":{"7":753,"N":"MrPerfect1316"},"9048214":{"7":911,"N":"Singlodo"},"9066933":{"7":1032,"N":"mdgerberich"},"9071943":{"7":829,"N":"jostholhuijsen"},"9082908":{"7":925,"N":"KillerPanda7624"},"9085216":{"7":1202,"N":"4o3haq28b"},"9104177":{"7":854,"N":"LNLEE33"},"9111280":{"7":903,"N":"andres_5493"},"9125585":{"7":1200,"N":"小熊維尼"},"9153644":{"7":1474,"N":"(PNG)Ultthor"},"9172676":{"7":1173,"N":"台版吊打"},"9177175":{"7":1040,"N":"overfuker"},"9203863":{"7":1217,"N":"晴天一柱"},"9216977":{"7":939,"N":"Heccal23"},"9223616":{"7":867,"N":"no-K-nic"},"9226223":{"7":1281,"N":"yellowbegger"},"9259136":{"7":1078,"N":"greve"},"9279069":{"7":846,"N":"NEXUS2C"},"9282951":{"7":683,"N":"Toaster Oven"},"9291137":{"7":936,"N":"brayperm7"},"9303699":{"7":882,"N":"[RYCTN] Signor Baraccia"},"9332145":{"7":1206,"N":"Azurewrath"},"9332162":{"7":1133,"N":"limsijun"},"9340212":{"7":977,"N":"ARJ_AOE"},"9382930":{"7":771,"N":"torpeda"},"9392349":{"7":862,"N":"dodo9230"},"9393334":{"7":1004,"N":"twitch.tv/zucaplaycl"},"9449579":{"7":1508,"N":"Mau Industrial"},"9456139":{"7":457,"N":"CactusGenie6"},"9459145":{"7":992,"N":"b100_oleg#ShadowRust"},"9463293":{"7":1192,"N":"[aM] Ale Vai"},"9500462":{"7":569,"N":"EF"},"9505135":{"7":1179,"N":"Ojabun"},"9572029":{"7":809,"N":"carloscanon98"},"9575626":{"7":1066,"N":"Ardenus2227"},"9577820":{"7":1007,"N":"Cottager"},"9600405":{"7":521,"N":"LoStMinerr"},"9623417":{"7":1042,"N":"alex_123"},"9636556":{"7":1200,"N":"Meta"},"9641549":{"7":1051,"N":"seba_frias"},"9658013":{"7":1021,"N":"Jordan"},"9659039":{"7":986,"N":"a chicken's fat dumpy"},"9669417":{"7":877,"N":"ROSSI"},"9681250":{"7":633,"N":"SoulCrushr"},"9685470":{"7":798,"N":"sr.omersari"},"9687023":{"7":853,"N":"tokerxion"},"9692541":{"7":1012,"N":"Naer4401"},"9696709":{"7":990,"N":"Altrocanto"},"9706806":{"7":881,"N":"Ricky Rascame"},"9715305":{"7":1278,"N":"新手型陸龜"},"9723455":{"7":670,"N":"gadorro91"},"9730659":{"7":991,"N":"PocketTreasures"},"9740473":{"7":365,"N":"turborecycler"},"9743597":{"7":779,"N":"RS576119"},"9743770":{"7":774,"N":"frandm94"},"9743971":{"7":1104,"N":"mugur.andrei.gheorghe"},"9744972":{"7":892,"N":"SIR OZ PENDRAGON"},"9750255":{"7":299,"N":"Sayakuat69"},"9754373":{"7":1542,"N":"uel"},"9755325":{"7":1110,"N":"Baberum"},"9773415":{"7":805,"N":"kaan4545"},"9774562":{"7":945,"N":"Argillac"},"9784328":{"7":1008,"N":"sweetcoffeemale"},"9788284":{"7":942,"N":"Enkindu17"},"9789762":{"7":1223,"N":"Andy@Hot.Summer"},"9794537":{"7":741,"N":"martin.augu"},"9799746":{"7":779,"N":"olajnik"},"9802592":{"7":766,"N":"1v9"},"9803757":{"7":1255,"N":"BO21 | Cr3w"},"9824796":{"7":490,"N":"Emreyldz"},"9840499":{"7":1007,"N":"The Young Eagle"},"9844933":{"7":1232,"N":"Arthedain"},"9847665":{"7":746,"N":"Brad8"},"9848398":{"7":947,"N":"M"},"9850386":{"7":844,"N":"l.lantermo"},"9855946":{"7":635,"N":"fdjz2112"},"9862921":{"7":954,"N":"dchenoweth96"},"9883129":{"7":843,"N":"Spanner"},"9883930":{"7":839,"N":"Hercule Poirot II"},"9885688":{"7":815,"N":"ALVAREZ7916"},"9893238":{"7":1213,"N":"Combi | Long.Pollo"},"9901888":{"7":666,"N":"yameisofi"},"9912050":{"7":791,"N":"SCT-4-2-4"},"9935024":{"7":643,"N":"Alvarinho1987"},"9938753":{"7":1589,"N":"GL.TheChampion_AoE"},"9945479":{"7":781,"N":"they lived happily ever after"},"9964665":{"7":946,"N":"LadiesMan217"},"9978380":{"7":813,"N":"Edison Flores Valera"},"9979071":{"7":1051,"N":"yerko.mitrovic"},"9979993":{"7":1015,"N":"Kaisar"},"9984708":{"7":1129,"N":"INKAS | Cazador De Smurf"},"9988054":{"7":905,"N":"_Zorbaz"},"10002690":{"7":952,"N":"fblcfc"},"10017479":{"7":515,"N":"tacio_gs"},"10030496":{"7":371,"N":"PARUS8931"},"10038823":{"7":970,"N":"DeJaVu"},"10039252":{"7":1009,"N":"Player39516211"},"10053844":{"7":797,"N":"Loreson314"},"10058322":{"7":1088,"N":"Woodrow F Call"},"10064418":{"7":1043,"N":"Morew"},"10085151":{"7":1347,"N":"刀哥"},"10085784":{"7":946,"N":"Kaspi"},"10090102":{"7":941,"N":"zt198204232022"},"10091576":{"7":776,"N":"DiegoDiez103846"},"10099416":{"7":983,"N":"skandalo"},"10099689":{"7":557,"N":"Evan_Turk132"},"10100105":{"7":1022,"N":"ACQ"},"10109058":{"7":1141,"N":"Čudlajs"},"10109211":{"7":689,"N":"Mnemosye_"},"10113188":{"7":998,"N":"chrishaegele"},"10125212":{"7":816,"N":"Neederbean"},"10131349":{"7":1012,"N":"Kozgen"},"10134563":{"7":941,"N":"La Araña blanca"},"10136330":{"7":1150,"N":"摸鱼"},"10139815":{"7":899,"N":"watanist"},"10152532":{"7":1043,"N":"MARIAN"},"10155426":{"7":1057,"N":"Batu khan"},"10156904":{"7":795,"N":"a.b.guwahati22"},"10159080":{"7":875,"N":"BananaWednesday"},"10177156":{"7":812,"N":"warkillking"},"10180842":{"7":1330,"N":"Upnotmity666"},"10181362":{"7":881,"N":"Brisael Grados R"},"10184263":{"7":923,"N":"El Pato Magno"},"10184860":{"7":650,"N":"castrofelipe203"},"10196566":{"7":801,"N":"j.rojaszelada"},"10197608":{"7":1177,"N":"Ranger-Lee"},"10198899":{"7":898,"N":"Hey Orange"},"10221862":{"7":1087,"N":"E4Everyone"},"10234027":{"7":1087,"N":"irving926"},"10239192":{"7":1335,"N":"Fearless Raja"},"10257714":{"7":556,"N":"patomar3421"},"10261000":{"7":1235,"N":"NovelMajesty"},"10277241":{"7":743,"N":"德罗蒙舰长3ychong尾号0131"},"10285881":{"7":889,"N":"YEYE"},"10296229":{"7":903,"N":"biest slayer"},"10304772":{"7":1125,"N":"逮玩狼"},"10307006":{"7":886,"N":"&xeel $helby Party"},"10309103":{"7":1291,"N":"IXAM"},"10312841":{"7":1057,"N":"LieutenantHawkeye"},"10322818":{"7":1017,"N":"温柔的旗木先生"},"10337153":{"7":940,"N":"ČÁVO JUAN"},"10341626":{"7":845,"N":"Ragnar Lodbrok"},"10341675":{"7":884,"N":"Bala"},"10358304":{"7":1195,"N":"Exile | Kaninchen"},"10370046":{"7":964,"N":"Temuyin"},"10375459":{"7":1068,"N":"cash money"},"10400746":{"7":842,"N":"ivanbastarrica"},"10415096":{"7":877,"N":"Dogga"},"10419503":{"7":913,"N":"Alien"},"10427182":{"7":1015,"N":"WeedIsland"},"10433777":{"7":1025,"N":"Galenicus007"},"10433779":{"7":958,"N":"SJD"},"10434209":{"7":891,"N":"=LORD="},"10443390":{"7":866,"N":"275602569"},"10448993":{"7":1164,"N":"the_kupre"},"10480672":{"7":1077,"N":"Wander"},"10485087":{"7":906,"N":"Rompejopos"},"10485432":{"7":855,"N":"kameradpopov"},"10491694":{"7":936,"N":"偷家王"},"10503180":{"7":1098,"N":"镇元大仙"},"10505903":{"7":900,"N":"DBXIB"},"10516112":{"7":1195,"N":"金戈铁鸡"},"10517703":{"7":828,"N":"Awad bin Laden本·拉登"},"10520066":{"7":959,"N":"hzr"},"10541189":{"7":1000,"N":"徇亓"},"10553341":{"7":931,"N":"INKAS | Gatufact"},"10554370":{"7":517,"N":"Johnnie Walker"},"10567834":{"7":1050,"N":"Itachi94"},"10581686":{"7":1032,"N":"ipst.samuel"},"10591993":{"7":918,"N":"JeiDeSAI"},"10592426":{"7":1125,"N":"Seft Corgo"},"10592472":{"7":1014,"N":"toot n boot"},"10613635":{"7":888,"N":"Paragon"},"10616560":{"7":887,"N":"dancloey12"},"10632959":{"7":692,"N":"BowserPesi"},"10641305":{"7":749,"N":"花序"},"10649410":{"7":647,"N":"czde96"},"10658424":{"7":878,"N":"LordCharles87"},"10680255":{"7":708,"N":"ilzoneto2014"},"10684811":{"7":876,"N":"sandrosuplauber"},"10698576":{"7":756,"N":"Mojo_Jojo"},"10708171":{"7":963,"N":"帝国逍遥王"},"10713853":{"7":851,"N":"英雄联盟万岁"},"10730444":{"7":989,"N":"Lautaro4239"},"10734986":{"7":1227,"N":"Kejserguldbajer 2."},"10747495":{"7":1124,"N":"Trexx34"},"10751255":{"7":886,"N":"Nicodie09"},"10755320":{"7":1107,"N":"IamJake"},"10755739":{"7":996,"N":"Alexis Á"},"10759689":{"7":994,"N":"RA"},"10760244":{"7":945,"N":"MadMatter"},"10765316":{"7":958,"N":"heatpumpparty"},"10815174":{"7":1171,"N":"malpaZmlotkiem"},"10818995":{"7":974,"N":"wheatharvester"},"10819927":{"7":1294,"N":"兜兜转转"},"10823256":{"7":1082,"N":"joao"},"10827392":{"7":1171,"N":"呵呵"},"10843464":{"7":1023,"N":"Tiago Avila"},"10865058":{"7":933,"N":"Ariel Gomez"},"10885484":{"7":850,"N":"Stoned Dragon"},"10908115":{"7":593,"N":"tobiii_69"},"10915772":{"7":1132,"N":"jjeeff06"},"10918589":{"7":960,"N":"rgl_aron"},"10922463":{"7":1249,"N":"Shadowking"},"10933550":{"7":713,"N":"TaurineBobcat21"},"10950829":{"7":909,"N":"cyrilvalat"},"10958790":{"7":1115,"N":"_Cactus_Viking"},"10973656":{"7":991,"N":"cpowers15"},"10976794":{"7":639,"N":"mateowen"},"10988582":{"7":851,"N":"tomtomtomtomtomtomtomtomtomtom"},"10990866":{"7":1229,"N":"Le Stratège"},"11036173":{"7":1241,"N":"andrescaceres3333333"},"11077255":{"7":800,"N":"1612531677"},"11113729":{"7":881,"N":"Shimmer"},"11180016":{"7":860,"N":"Hunter"},"11193363":{"7":877,"N":"Yakill"},"11223298":{"7":1601,"N":"summer"},"11223994":{"7":1155,"N":"1633131486"},"11224124":{"7":848,"N":"King of King"},"11224241":{"7":881,"N":"ismensa"},"11228506":{"7":1204,"N":"Tony Torsi"},"11237809":{"7":1069,"N":"Go easy, alright?"},"11239213":{"7":986,"N":"dambo"},"11242675":{"7":710,"N":"delnaru3"},"11249494":{"7":742,"N":"marquitosrock"},"11255442":{"7":792,"N":"SwartKat"},"11257686":{"7":1789,"N":"HOWL.Kozmo"},"11258581":{"7":1043,"N":"danerpsy"},"11272027":{"7":986,"N":"abelspm14"},"11276511":{"7":850,"N":"LaVenganzaDelTOWERSCLAN"},"11283252":{"7":817,"N":"Infierno TOWER'S CLAN"},"11289662":{"7":590,"N":"Chris G"},"11300815":{"7":1361,"N":"AndyThePro"},"11311056":{"7":682,"N":"Lil Doppey"},"11311973":{"7":797,"N":"416472309"},"11312692":{"7":1304,"N":"andy24990"},"11318736":{"7":973,"N":"Lord_xc"},"11319150":{"7":969,"N":"umit.A"},"11321553":{"7":874,"N":"Bahus"},"11322490":{"7":597,"N":"2024793269"},"11343963":{"7":720,"N":"SandovalBastian2002"},"11370071":{"7":632,"N":"Gonzalomvm"},"11378476":{"7":715,"N":"imortalis12"},"11393062":{"7":1340,"N":"youteGG_smurf"},"11396624":{"7":1343,"N":"Kuriboh"},"11404709":{"7":1044,"N":"richardanethan"},"11407053":{"7":621,"N":"Shardes BUYSKINS.RU"},"11410778":{"7":893,"N":"335149010"},"11413036":{"7":809,"N":"kikoparket"},"11422988":{"7":799,"N":"NerdZoma"},"11423469":{"7":774,"N":"Esquilo19"},"11426234":{"7":714,"N":"ElMalandra#33"},"11436942":{"7":990,"N":"2 Dev 553136079"},"11459759":{"7":981,"N":"The Black Denisiña"},"11469763":{"7":1098,"N":"happyfarmer"},"11473980":{"7":1081,"N":"nameless13111"},"11478411":{"7":764,"N":"Shawn"},"11481952":{"7":1251,"N":"Tesla"},"11484361":{"7":858,"N":"10086"},"11491590":{"7":976,"N":"Bloody"},"11506044":{"7":1037,"N":"Thích Vui Vẻ"},"11518005":{"7":912,"N":"HeinzRuehmann"},"11539366":{"7":922,"N":"mayayo"},"11541403":{"7":877,"N":"pkaoe"},"11545678":{"7":1040,"N":"S.T.ILICITANO"},"11547380":{"7":992,"N":"2IdleVillagers"},"11551814":{"7":1107,"N":"LightningBlade"},"11554975":{"7":1034,"N":"513646378"},"11566292":{"7":945,"N":"瞬间的美好"},"11574856":{"7":1003,"N":"tzutzu91"},"11576378":{"7":838,"N":"Hephaestus"},"11579168":{"7":978,"N":"NEMAGOVE"},"11617746":{"7":1094,"N":"SLT七夜的许愿星"},"11623163":{"7":834,"N":"Work Hard, Play Hard"},"11627942":{"7":865,"N":"enessarc"},"11630787":{"7":1109,"N":"kyuss"},"11631988":{"7":1133,"N":"KEKO4931"},"11652871":{"7":927,"N":"Hopeless"},"11662097":{"7":780,"N":"estebanpa2000"},"11664255":{"7":1054,"N":"DrAllAroundandAbout"},"11669002":{"7":1166,"N":"adriaalva97"},"11676502":{"7":1053,"N":"wigglepuppy24"},"11676937":{"7":653,"N":"Cilezator"},"11679051":{"7":602,"N":"rowgueroze"},"11693305":{"7":617,"N":"bttdavy1"},"11697466":{"7":957,"N":"AbZurdo"},"11702960":{"7":856,"N":"Nico"},"11704127":{"7":1234,"N":"edalmavuz"},"11707859":{"7":1080,"N":"KlinKlin"},"11716162":{"7":1007,"N":"Yakuza"},"11720275":{"7":904,"N":"Squirrel Viking"},"11740626":{"7":933,"N":"机器猫"},"11747100":{"7":833,"N":"cipi"},"11748418":{"7":852,"N":"bianfa54"},"11759152":{"7":661,"N":"我他妈来了"},"11766043":{"7":916,"N":"thijmenplomp"},"11766579":{"7":763,"N":"班长带头谈恋爱"},"11768331":{"7":507,"N":"Badman"},"11769102":{"7":956,"N":"BlukuUktan"},"11778785":{"7":147,"N":"cnkkrt"},"11787241":{"7":1049,"N":"gguowenfu8637"},"11795633":{"7":1011,"N":"TheBaztard"},"11821664":{"7":970,"N":"faintingdonkey"},"11822322":{"7":952,"N":"Artorius"},"11834199":{"7":469,"N":"michael.j.springer"},"11841667":{"7":893,"N":"Keyser Soze"},"11845401":{"7":878,"N":"[SaZ] Baldas"},"11848015":{"7":657,"N":"dincerceri"},"11849138":{"7":924,"N":"leandore"},"11851229":{"7":1045,"N":"Minimugre"},"11855127":{"7":905,"N":"RKO"},"11855890":{"7":920,"N":"jhopp"},"11861495":{"7":1051,"N":"goupher"},"11876218":{"7":1162,"N":"Blue"},"11882976":{"7":837,"N":"q51866921"},"11888066":{"7":970,"N":"Cabezon"},"11938155":{"7":743,"N":"muddred12"},"11972649":{"7":722,"N":"ivanmusica1990"},"11983563":{"7":1183,"N":"Toaster"},"11989410":{"7":1041,"N":"El_ChecheTV"},"12000866":{"7":1011,"N":"Zega"},"12017449":{"7":1109,"N":"KarlMax"},"12018088":{"7":933,"N":"madalinananana"},"12029123":{"7":1119,"N":"stasia.allison"},"12030792":{"7":1204,"N":"Anton The Great"},"12052080":{"7":932,"N":"Darius The Big"},"12058683":{"7":672,"N":"valeria"},"12061874":{"7":826,"N":"Ace of Shovels"},"12065533":{"7":581,"N":"TommyWiseau22"},"12072509":{"7":743,"N":"DceCylia"},"12080710":{"7":918,"N":"GameWatcher"},"12094368":{"7":687,"N":"小飞刀来闹"},"12109077":{"7":1214,"N":"1361376639"},"12127863":{"7":787,"N":"Edelmut"},"12134577":{"7":1024,"N":"sndfreia"},"12144573":{"7":807,"N":"baka030"},"12154769":{"7":796,"N":"Kaia masca coca serrano"},"12157506":{"7":986,"N":"MilkMaster08"},"12166376":{"7":933,"N":"melkor135"},"12166641":{"7":946,"N":"Der_Kommissar"},"12205472":{"7":788,"N":"spontanamans"},"12248613":{"7":729,"N":"TKPeanut21450"},"12249507":{"7":1060,"N":"neal"},"12249685":{"7":1227,"N":"[JOJO] ROAD ROLLER"},"12251606":{"7":1652,"N":"DreamCl"},"12259109":{"7":517,"N":"orientalrug"},"12273309":{"7":866,"N":"WILD CHEKoO"},"12279281":{"7":1006,"N":"ivzarleinad"},"12296300":{"7":863,"N":"3560877396"},"12341942":{"7":1078,"N":"majekf"},"12351259":{"7":812,"N":"Alpha Pie"},"12372730":{"7":1321,"N":"Free Armour Trimming"},"12373313":{"7":754,"N":"EliasCar"},"12378843":{"7":935,"N":"matarife13"},"12392445":{"7":822,"N":"GengisKangC137"},"12417740":{"7":812,"N":"Murd3rfce"},"12417936":{"7":718,"N":"wlabellavita"},"12440797":{"7":889,"N":"罗布泊勇士小聂"},"12449343":{"7":1040,"N":"seedsofchangelc"},"12469960":{"7":598,"N":"Bas Rutten89"},"12564898":{"7":739,"N":"REI DELAS"},"12706148":{"7":821,"N":"P Friendly"},"12708102":{"7":692,"N":"ing.adrian.trevino.gro"},"12753735":{"7":1108,"N":"sosa89106"},"12781590":{"7":780,"N":"mariuszz490"},"12794924":{"7":572,"N":"carlo kaky"},"12802993":{"7":585,"N":"Dialexxandro"},"12832675":{"7":710,"N":"w BinGo w"},"12947821":{"7":840,"N":"abcd7426lbj"},"12963945":{"7":596,"N":"iAmFeegiTeeth"},"13248098":{"7":866,"N":"RaqueLB8998"},"13281932":{"7":614,"N":"Chr0niXXX"},"13387389":{"7":1202,"N":"Myth"},"13399329":{"7":779,"N":"ChalkyGolf98753"},"13497524":{"7":915,"N":"Feloko95"},"13511351":{"7":890,"N":"Bubus"},"13634944":{"7":1089,"N":"Santafereño41"},"13640892":{"7":733,"N":"CrudeBorne"},"13674902":{"7":607,"N":"patrichs.ordenes"},"13690942":{"7":1084,"N":"2Alarms59286"},"13701247":{"7":658,"N":"DjNiceHole"},"13709261":{"7":1621,"N":"AdrenStrat"},"13755869":{"7":1024,"N":"Euriko1760"},"13807426":{"7":965,"N":"2659621113"},"13954426":{"7":981,"N":"alperbozo"},"13959474":{"7":933,"N":"prof.helder"},"13964456":{"7":944,"N":"jferrada340"},"13966867":{"7":1063,"N":"CubeVilly"},"13967423":{"7":850,"N":"STALKER7"},"14010897":{"7":1008,"N":"lozanocruzaleyt"},"14029090":{"7":726,"N":"rafael.ortiz.va"},"14042437":{"7":639,"N":"MrSotoSir"},"14046467":{"7":1011,"N":"Ponyagi"},"14187529":{"7":696,"N":"ClaretSoup26419"},"14193237":{"7":749,"N":"eduard.ft"},"14193496":{"7":845,"N":"CaptOblivious"},"14200338":{"7":727,"N":"__RELiG"},"14206414":{"7":499,"N":"leoHDXD2"},"14257396":{"7":1294,"N":"sodsojf"},"14293214":{"7":926,"N":"ivan.buturajac"},"14355382":{"7":764,"N":"McFLYsilla"},"14374318":{"7":617,"N":"thewhiteman8860"},"14386738":{"7":802,"N":"TrakaTra"},"14444512":{"7":1433,"N":"Black Forest"},"14449805":{"7":964,"N":"Sarahsberas"},"14452930":{"7":681,"N":"santayo_8"},"14465980":{"7":344,"N":"Ambett"},"14476203":{"7":899,"N":"Cacique"},"14514650":{"7":1073,"N":"Mikola_UA"},"14524404":{"7":896,"N":"Alper"},"14541444":{"7":1087,"N":"SalmonArepa"},"14577186":{"7":897,"N":"shaulitox"},"14611569":{"7":973,"N":"Partié"},"14625149":{"7":676,"N":"General W"},"14630914":{"7":872,"N":"leosalmon6"},"14659505":{"7":806,"N":"azabache"},"14690440":{"7":706,"N":"norbyfontana98"},"14704481":{"7":910,"N":"ProCrazyBR8223"},"14712613":{"7":722,"N":"alegiuliani2000"},"14731952":{"7":984,"N":"Xilocreo"},"14739960":{"7":1016,"N":"Captain Horatius"},"14745876":{"7":701,"N":"hxxxc"},"14775300":{"7":992,"N":"Mangokul"},"14785156":{"7":1126,"N":"-Ghost-"},"14808242":{"7":868,"N":"clarkey771"},"14815765":{"7":1257,"N":"Paquita Cabeza"},"14816922":{"7":955,"N":"CyberSune"},"14817690":{"7":726,"N":"marzszam"},"14832485":{"7":956,"N":"HeavySilence"},"14861655":{"7":885,"N":"pablorf_93"},"14875157":{"7":932,"N":"rahbeehtwa"},"14924087":{"7":1199,"N":"珊瑚宫心海"},"14944457":{"7":850,"N":"joetal1"},"14955503":{"7":842,"N":"AndyfSoto"},"14988579":{"7":446,"N":"hornetfour"},"14989502":{"7":790,"N":"Gondar"},"14999763":{"7":710,"N":"Porter184"},"15011917":{"7":838,"N":"DuRex"},"15019717":{"7":801,"N":"briglor"},"15029839":{"7":892,"N":"lautiman"},"15030523":{"7":814,"N":"chad-gibbons"},"15031415":{"7":1056,"N":"Master123Oswi"},"15034701":{"7":870,"N":"LaAcadeRC22"},"15040300":{"7":583,"N":"EKKAP"},"15058312":{"7":884,"N":"Quadryzx"},"15068245":{"7":735,"N":"nihan.zengin2"},"15072369":{"7":819,"N":"Rafron"},"15072869":{"7":804,"N":"Max_Payne"},"15124446":{"7":678,"N":"alexng.200612"},"15125041":{"7":902,"N":"Loongyang"},"15129144":{"7":941,"N":"ezequielleonardorodriguez"},"15152759":{"7":661,"N":"matthewraymondw"},"15161885":{"7":1058,"N":"Romanos 9"},"15162684":{"7":634,"N":"lespimpolo1"},"15163953":{"7":871,"N":"DadBotDers"},"15177476":{"7":933,"N":"thimbre3"},"15191156":{"7":746,"N":"alan.caputo11"},"15191225":{"7":678,"N":"ODENN"},"15198243":{"7":1332,"N":"towncenterrusher"},"15204183":{"7":593,"N":"Nito_Dante [FC]"},"15214165":{"7":1503,"N":"SalaDin"},"15218847":{"7":841,"N":"---ANDREE---"},"15246266":{"7":695,"N":"tiagobiz"},"15261643":{"7":671,"N":"feliped_gs"},"15264630":{"7":699,"N":"Ikkimora"},"15274437":{"7":722,"N":"NIKO"},"15305398":{"7":739,"N":"StrongWolf91512"},"15306875":{"7":1128,"N":"ShapeOfMyCock"},"15308032":{"7":738,"N":"Killmenez94"},"15312610":{"7":804,"N":"ZeusDurrant"},"15314469":{"7":1353,"N":"Viejo_Sabrozo"},"15328111":{"7":1068,"N":"Pedrolopez13"},"15335812":{"7":1047,"N":"tecknokid15"},"15382671":{"7":866,"N":"Patoshik"},"15385970":{"7":917,"N":"aleberontastro"},"15393144":{"7":946,"N":"Shancer"},"15396768":{"7":761,"N":"bobipiciu"},"15416335":{"7":851,"N":"Comunidad_AOE2"},"15420419":{"7":709,"N":"christianzea"},"15423252":{"7":1248,"N":"Battle beast"},"15426615":{"7":707,"N":"albert.mv89"},"15431985":{"7":765,"N":"GreyHarry the VII"},"15456571":{"7":872,"N":"Scolethal"},"15463269":{"7":905,"N":"X1K"},"15470558":{"7":1119,"N":"mitchell_bombers"},"15474622":{"7":989,"N":"Rayeus"},"15479124":{"7":1325,"N":"ML | Angel_Nuud"},"15484112":{"7":624,"N":"thanglop10a1"},"15484598":{"7":515,"N":"ZaitsevCO"},"15498079":{"7":982,"N":"BluePrinceTheBillions"},"15505547":{"7":857,"N":"whic42"},"15508610":{"7":836,"N":"w2391926876"},"15511585":{"7":703,"N":"ggkushh"},"15514889":{"7":966,"N":"Qi.."},"15527762":{"7":630,"N":"OhRely"},"15532550":{"7":785,"N":"AgeConqueror"},"15538084":{"7":495,"N":"EL Michi"},"15540507":{"7":1225,"N":"Videira_GT"},"15541980":{"7":941,"N":"Virus"},"15544408":{"7":904,"N":"Beto"},"15546339":{"7":655,"N":"ELadri"},"15557801":{"7":982,"N":"bobby14"},"15566419":{"7":1076,"N":"MarSpa"},"15570547":{"7":618,"N":"jokii7070"},"15573149":{"7":520,"N":"moebi-nadja"},"15573503":{"7":822,"N":"Whitefox_returns"},"15575012":{"7":540,"N":"CHUPAPIN"},"15592925":{"7":752,"N":"ARTUR_FAN"},"15594163":{"7":704,"N":"camoctezuma2000"},"15600145":{"7":790,"N":"毛概"},"15611232":{"7":1212,"N":"Komsomol"},"15614771":{"7":752,"N":"ARTİST"},"15626988":{"7":1116,"N":"aliasmail50"},"15630774":{"7":856,"N":"nobrains110"},"15633551":{"7":488,"N":"fulyaokat"},"15635840":{"7":795,"N":"Guts"},"15647241":{"7":717,"N":"Spynaren"},"15648155":{"7":1246,"N":"Regina Phalange"},"15654862":{"7":825,"N":"Devdas"},"15675694":{"7":908,"N":"pawel9o"},"15687980":{"7":959,"N":"KAYSER"},"15704120":{"7":759,"N":"Moroz_420"},"15720253":{"7":1023,"N":"Mugiwara Emperor of the Sea"},"15732334":{"7":880,"N":"Bazuca"},"15750003":{"7":868,"N":"eXadr"},"15760453":{"7":1251,"N":"noobushek"},"15781618":{"7":1402,"N":"jozkoferko"},"15785293":{"7":938,"N":"sarahgrace09"},"15800953":{"7":881,"N":"reflerr"},"15896077":{"7":623,"N":"rafuki00"},"15920467":{"7":999,"N":"你瞎玩我就瞎玩"},"15944098":{"7":912,"N":"SiFwtKwizda"},"16016019":{"7":800,"N":"Vico_aubin2000"},"16022916":{"7":1141,"N":"TremmyAR"}}}