{"timestamp":1713054714458.1968,"data":{"6165":{"1":1619,"N":"KoD_Dru1d"},"182749":{"1":1930,"N":"The_Dragonstar"},"214031":{"1":1516,"N":"Hamza"},"217750":{"1":1316,"N":"man"},"225852":{"1":1381,"N":"L_S_D_D_S_L"},"228375":{"1":1661,"N":"L3af"},"232987":{"1":1655,"N":"boOmstik"},"259483":{"1":1603,"N":"BananA"},"267387":{"1":1205,"N":"XavierTenka"},"271202":{"1":1849,"N":"SalzZ_Vinchester"},"283216":{"1":1736,"N":"MaJoR_Kd"},"283384":{"1":1622,"N":"[Valhalla] The Otter One"},"307266":{"1":1207,"N":"Bob the Builder"},"467602":{"1":1450,"N":"LTD BuzzLightYEar19"},"473462":{"1":1705,"N":"Maldhar"},"509112":{"1":1945,"N":"ffavorite_1"},"584824":{"1":1882,"N":"True"},"589705":{"1":1338,"N":"[Real] GoLoUm25"},"591696":{"1":1653,"N":"Nova_8"},"648247":{"1":1013,"N":"nicolascageofempires"},"691523":{"1":948,"N":"Stefananna"},"695771":{"1":1056,"N":"Delf"},"696377":{"1":1449,"N":"m1lky"},"698101":{"1":1796,"N":"Zayu"},"712321":{"1":1182,"N":"BENTOR"},"794681":{"1":1412,"N":"StrikeMuffin"},"839529":{"1":1852,"N":"www.twitch.tv/ultra_coming"},"1074101":{"1":1174,"N":"neverisland2"},"1239103":{"1":1355,"N":"Unknown"},"1358482":{"1":1494,"N":"kamrat qp"},"1627747":{"1":1394,"N":"Kr1lle"},"1694092":{"1":1080,"N":"Jason_AOE"},"1750569":{"1":1589,"N":"Viva La Omer"},"2048591":{"1":1874,"N":"QuEnDi_kelar"},"2060201":{"1":1411,"N":"[Decrepit] Arch Angel"},"2285540":{"1":1527,"N":"Korea"},"2385419":{"1":1568,"N":"WiSeMaN"},"2653793":{"1":2175,"N":"Frost_9"},"2796802":{"1":1424,"N":"FireSaga_"},"2871576":{"1":1920,"N":"HazZy"},"3444509":{"1":1567,"N":"Mununez"},"4158077":{"1":1202,"N":"Chirp"},"4711570":{"1":1221,"N":"FrameshiftMutation"},"4720302":{"1":1027,"N":"Ritas2409"},"5186718":{"1":1747,"N":"Zaryab"},"5649904":{"1":1151,"N":"K A N Y E"},"5734826":{"1":1381,"N":"ANTIFA"},"6023176":{"1":1400,"N":"LeGenD"},"6064772":{"1":1038,"N":"olivaresgol12"},"6108190":{"1":962,"N":"Manu Olivares"},"6312991":{"1":1442,"N":"Breeze_"},"6844536":{"1":1727,"N":"SuNo_TwEpY"},"6892324":{"1":1087,"N":"Angry Bull"},"9091460":{"1":888,"N":"Admiral Zhao"},"9866208":{"1":1612,"N":"uakonz"},"10224355":{"1":930,"N":"Ulises 9172"},"11622635":{"1":1317,"N":"Oxygen_"},"12615440":{"1":1165,"N":"Danniel1775124"},"14790812":{"1":1400,"N":"Rastaman9482"},"16998893":{"1":1523,"N":"Frank"},"17856344":{"1":966,"N":"Composure"},"18835299":{"1":1426,"N":"LimeTree"},"18876302":{"1":914,"N":"ztniko_anti666"}}}